{"6010000":{"prefectureJa":"京都府","cityJa":"京都市南区","townJa":"以下に掲載がない場合","prefectureEn":"KYOTO FU","cityEn":"KYOTO SHI MINAMI KU","townEn":"IKANIKEISAIGANAIBAAI"},"6010101":{"prefectureJa":"京都府","cityJa":"京都市北区","townJa":"真弓八幡町","prefectureEn":"KYOTO FU","cityEn":"KYOTO SHI KITA KU","townEn":"MAYUMI HACHIMANCHO"},"6010102":{"prefectureJa":"京都府","cityJa":"京都市北区","townJa":"真弓善福","prefectureEn":"KYOTO FU","cityEn":"KYOTO SHI KITA KU","townEn":"MAYUMI ZEMPUKU"},"6010111":{"prefectureJa":"京都府","cityJa":"京都市北区","townJa":"杉阪北尾","prefectureEn":"KYOTO FU","cityEn":"KYOTO SHI KITA KU","townEn":"SUGISAKA KITAO"},"6010112":{"prefectureJa":"京都府","cityJa":"京都市北区","townJa":"杉阪都町","prefectureEn":"KYOTO FU","cityEn":"KYOTO SHI KITA KU","townEn":"SUGISAKA MIYAKOCHO"},"6010113":{"prefectureJa":"京都府","cityJa":"京都市北区","townJa":"杉阪道風町","prefectureEn":"KYOTO FU","cityEn":"KYOTO SHI KITA KU","townEn":"SUGISAKA TOFUCHO"},"6010121":{"prefectureJa":"京都府","cityJa":"京都市北区","townJa":"中川東山","prefectureEn":"KYOTO FU","cityEn":"KYOTO SHI KITA KU","townEn":"NAKAGAWA HIGASHIYAMA"},"6010122":{"prefectureJa":"京都府","cityJa":"京都市北区","townJa":"中川北山町","prefectureEn":"KYOTO FU","cityEn":"KYOTO SHI KITA KU","townEn":"NAKAGAWA KITAYAMACHO"},"6010123":{"prefectureJa":"京都府","cityJa":"京都市北区","townJa":"中川西山","prefectureEn":"KYOTO FU","cityEn":"KYOTO SHI KITA KU","townEn":"NAKAGAWA NISHIYAMA"},"6010124":{"prefectureJa":"京都府","cityJa":"京都市北区","townJa":"中川中山","prefectureEn":"KYOTO FU","cityEn":"KYOTO SHI KITA KU","townEn":"NAKAGAWA NAKAYAMA"},"6010125":{"prefectureJa":"京都府","cityJa":"京都市北区","townJa":"中川川登","prefectureEn":"KYOTO FU","cityEn":"KYOTO SHI KITA KU","townEn":"NAKAGAWA KAWANOBORI"},"6010131":{"prefectureJa":"京都府","cityJa":"京都市北区","townJa":"小野下ノ町","prefectureEn":"KYOTO FU","cityEn":"KYOTO SHI KITA KU","townEn":"ONO SHIMONOCHO"},"6010132":{"prefectureJa":"京都府","cityJa":"京都市北区","townJa":"小野中ノ町","prefectureEn":"KYOTO FU","cityEn":"KYOTO SHI KITA KU","townEn":"ONO NAKANOCHO"},"6010133":{"prefectureJa":"京都府","cityJa":"京都市北区","townJa":"小野上ノ町","prefectureEn":"KYOTO FU","cityEn":"KYOTO SHI KITA KU","townEn":"ONO KAMINOCHO"},"6010134":{"prefectureJa":"京都府","cityJa":"京都市北区","townJa":"小野岩戸","prefectureEn":"KYOTO FU","cityEn":"KYOTO SHI KITA KU","townEn":"ONO IWATO"},"6010135":{"prefectureJa":"京都府","cityJa":"京都市北区","townJa":"小野宮ノ上町","prefectureEn":"KYOTO FU","cityEn":"KYOTO SHI KITA KU","townEn":"ONO MIYANOKAMICHO"},"6010141":{"prefectureJa":"京都府","cityJa":"京都市北区","townJa":"大森稲荷","prefectureEn":"KYOTO FU","cityEn":"KYOTO SHI KITA KU","townEn":"OMORI INARI"},"6010142":{"prefectureJa":"京都府","cityJa":"京都市北区","townJa":"大森芦堂町","prefectureEn":"KYOTO FU","cityEn":"KYOTO SHI KITA KU","townEn":"OMORI ASHIDOCHO"},"6010143":{"prefectureJa":"京都府","cityJa":"京都市北区","townJa":"大森中町","prefectureEn":"KYOTO FU","cityEn":"KYOTO SHI KITA KU","townEn":"OMORI NAKACHO"},"6010144":{"prefectureJa":"京都府","cityJa":"京都市北区","townJa":"大森西町","prefectureEn":"KYOTO FU","cityEn":"KYOTO SHI KITA KU","townEn":"OMORI NISHICHO"},"6010145":{"prefectureJa":"京都府","cityJa":"京都市北区","townJa":"大森東町","prefectureEn":"KYOTO FU","cityEn":"KYOTO SHI KITA KU","townEn":"OMORI HIGASHICHO"},"6010251":{"prefectureJa":"京都府","cityJa":"京都市右京区","townJa":"京北周山町","prefectureEn":"KYOTO FU","cityEn":"KYOTO SHI UKYO KU","townEn":"KEIHOKU SHUZANCHO"},"6010252":{"prefectureJa":"京都府","cityJa":"京都市右京区","townJa":"京北五本松町","prefectureEn":"KYOTO FU","cityEn":"KYOTO SHI UKYO KU","townEn":"KEIHOKU GOHOMMATSUCHO"},"6010261":{"prefectureJa":"京都府","cityJa":"京都市右京区","townJa":"京北柏原町","prefectureEn":"KYOTO FU","cityEn":"KYOTO SHI UKYO KU","townEn":"KEIHOKU KASHIWARACHO"},"6010262":{"prefectureJa":"京都府","cityJa":"京都市右京区","townJa":"京北細野町","prefectureEn":"KYOTO FU","cityEn":"KYOTO SHI UKYO KU","townEn":"KEIHOKU HOSONOCHO"},"6010263":{"prefectureJa":"京都府","cityJa":"京都市右京区","townJa":"京北弓槻町","prefectureEn":"KYOTO FU","cityEn":"KYOTO SHI UKYO KU","townEn":"KEIHOKU YUZUKICHO"},"6010264":{"prefectureJa":"京都府","cityJa":"京都市右京区","townJa":"京北栃本町","prefectureEn":"KYOTO FU","cityEn":"KYOTO SHI UKYO KU","townEn":"KEIHOKU TOCHIMOTOCHO"},"6010265":{"prefectureJa":"京都府","cityJa":"京都市右京区","townJa":"京北中地町","prefectureEn":"KYOTO FU","cityEn":"KYOTO SHI UKYO KU","townEn":"KEIHOKU CHUJICHO"},"6010266":{"prefectureJa":"京都府","cityJa":"京都市右京区","townJa":"京北下宇津町","prefectureEn":"KYOTO FU","cityEn":"KYOTO SHI UKYO KU","townEn":"KEIHOKU SHIMOTSUCHO"},"6010271":{"prefectureJa":"京都府","cityJa":"京都市右京区","townJa":"京北熊田町","prefectureEn":"KYOTO FU","cityEn":"KYOTO SHI UKYO KU","townEn":"KEIHOKU KUMATACHO"},"6010272":{"prefectureJa":"京都府","cityJa":"京都市右京区","townJa":"京北下熊田町","prefectureEn":"KYOTO FU","cityEn":"KYOTO SHI UKYO KU","townEn":"KEIHOKU SHIMOKUMATACHO"},"6010273":{"prefectureJa":"京都府","cityJa":"京都市右京区","townJa":"京北明石町","prefectureEn":"KYOTO FU","cityEn":"KYOTO SHI UKYO KU","townEn":"KEIHOKU AKESHICHO"},"6010274":{"prefectureJa":"京都府","cityJa":"京都市右京区","townJa":"京北浅江町","prefectureEn":"KYOTO FU","cityEn":"KYOTO SHI UKYO KU","townEn":"KEIHOKU AZAECHO"},"6010275":{"prefectureJa":"京都府","cityJa":"京都市右京区","townJa":"京北宇野町","prefectureEn":"KYOTO FU","cityEn":"KYOTO SHI UKYO KU","townEn":"KEIHOKU UNOCHO"},"6010276":{"prefectureJa":"京都府","cityJa":"京都市右京区","townJa":"京北西町","prefectureEn":"KYOTO FU","cityEn":"KYOTO SHI UKYO KU","townEn":"KEIHOKU NISHICHO"},"6010277":{"prefectureJa":"京都府","cityJa":"京都市右京区","townJa":"京北漆谷町","prefectureEn":"KYOTO FU","cityEn":"KYOTO SHI UKYO KU","townEn":"KEIHOKU URUSHITANICHO"},"6010278":{"prefectureJa":"京都府","cityJa":"京都市右京区","townJa":"京北矢代中町","prefectureEn":"KYOTO FU","cityEn":"KYOTO SHI UKYO KU","townEn":"KEIHOKU YASHIRONAKACHO"},"6010311":{"prefectureJa":"京都府","cityJa":"京都市右京区","townJa":"京北小塩町","prefectureEn":"KYOTO FU","cityEn":"KYOTO SHI UKYO KU","townEn":"KEIHOKU OSHIOCHO"},"6010312":{"prefectureJa":"京都府","cityJa":"京都市右京区","townJa":"京北初川町","prefectureEn":"KYOTO FU","cityEn":"KYOTO SHI UKYO KU","townEn":"KEIHOKU HATSUKAWACHO"},"6010313":{"prefectureJa":"京都府","cityJa":"京都市右京区","townJa":"京北井戸町","prefectureEn":"KYOTO FU","cityEn":"KYOTO SHI UKYO KU","townEn":"KEIHOKU IDOCHO"},"6010314":{"prefectureJa":"京都府","cityJa":"京都市右京区","townJa":"京北大野町","prefectureEn":"KYOTO FU","cityEn":"KYOTO SHI UKYO KU","townEn":"KEIHOKU ONOCHO"},"6010315":{"prefectureJa":"京都府","cityJa":"京都市右京区","townJa":"京北中江町","prefectureEn":"KYOTO FU","cityEn":"KYOTO SHI UKYO KU","townEn":"KEIHOKU NAKAECHO"},"6010316":{"prefectureJa":"京都府","cityJa":"京都市右京区","townJa":"京北比賀江町","prefectureEn":"KYOTO FU","cityEn":"KYOTO SHI UKYO KU","townEn":"KEIHOKU HIGAECHO"},"6010321":{"prefectureJa":"京都府","cityJa":"京都市右京区","townJa":"京北塔町","prefectureEn":"KYOTO FU","cityEn":"KYOTO SHI UKYO KU","townEn":"KEIHOKU TOCHO"},"6010322":{"prefectureJa":"京都府","cityJa":"京都市右京区","townJa":"京北辻町","prefectureEn":"KYOTO FU","cityEn":"KYOTO SHI UKYO KU","townEn":"KEIHOKU TSUJICHO"},"6010323":{"prefectureJa":"京都府","cityJa":"京都市右京区","townJa":"京北鳥居町","prefectureEn":"KYOTO FU","cityEn":"KYOTO SHI UKYO KU","townEn":"KEIHOKU TORIICHO"},"6010324":{"prefectureJa":"京都府","cityJa":"京都市右京区","townJa":"京北下町","prefectureEn":"KYOTO FU","cityEn":"KYOTO SHI UKYO KU","townEn":"KEIHOKU SHIMOCHO"},"6010401":{"prefectureJa":"京都府","cityJa":"京都市右京区","townJa":"京北片波町","prefectureEn":"KYOTO FU","cityEn":"KYOTO SHI UKYO KU","townEn":"KEIHOKU KATANAMICHO"},"6010402":{"prefectureJa":"京都府","cityJa":"京都市右京区","townJa":"京北上黒田町","prefectureEn":"KYOTO FU","cityEn":"KYOTO SHI UKYO KU","townEn":"KEIHOKU KAMIKURODACHO"},"6010403":{"prefectureJa":"京都府","cityJa":"京都市右京区","townJa":"京北灰屋町","prefectureEn":"KYOTO FU","cityEn":"KYOTO SHI UKYO KU","townEn":"KEIHOKU HAIYACHO"},"6010404":{"prefectureJa":"京都府","cityJa":"京都市右京区","townJa":"京北芹生町","prefectureEn":"KYOTO FU","cityEn":"KYOTO SHI UKYO KU","townEn":"KEIHOKU SERYOCHO"},"6010405":{"prefectureJa":"京都府","cityJa":"京都市右京区","townJa":"京北下黒田町","prefectureEn":"KYOTO FU","cityEn":"KYOTO SHI UKYO KU","townEn":"KEIHOKU SHIMOKURODACHO"},"6010406":{"prefectureJa":"京都府","cityJa":"京都市右京区","townJa":"京北宮町","prefectureEn":"KYOTO FU","cityEn":"KYOTO SHI UKYO KU","townEn":"KEIHOKU MIYACHO"},"6010531":{"prefectureJa":"京都府","cityJa":"京都市右京区","townJa":"京北上弓削町","prefectureEn":"KYOTO FU","cityEn":"KYOTO SHI UKYO KU","townEn":"KEIHOKU KAMIYUGECHO"},"6010532":{"prefectureJa":"京都府","cityJa":"京都市右京区","townJa":"京北上中町","prefectureEn":"KYOTO FU","cityEn":"KYOTO SHI UKYO KU","townEn":"KEIHOKU KAMINAKACHO"},"6010533":{"prefectureJa":"京都府","cityJa":"京都市右京区","townJa":"京北下中町","prefectureEn":"KYOTO FU","cityEn":"KYOTO SHI UKYO KU","townEn":"KEIHOKU SHIMONAKACHO"},"6010534":{"prefectureJa":"京都府","cityJa":"京都市右京区","townJa":"京北下弓削町","prefectureEn":"KYOTO FU","cityEn":"KYOTO SHI UKYO KU","townEn":"KEIHOKU SHIMOYUGECHO"},"6010535":{"prefectureJa":"京都府","cityJa":"京都市右京区","townJa":"京北井崎町","prefectureEn":"KYOTO FU","cityEn":"KYOTO SHI UKYO KU","townEn":"KEIHOKU IZAKICHO"},"6010536":{"prefectureJa":"京都府","cityJa":"京都市右京区","townJa":"京北塩田町","prefectureEn":"KYOTO FU","cityEn":"KYOTO SHI UKYO KU","townEn":"KEIHOKU SHIOTACHO"},"6010541":{"prefectureJa":"京都府","cityJa":"京都市右京区","townJa":"京北赤石町","prefectureEn":"KYOTO FU","cityEn":"KYOTO SHI UKYO KU","townEn":"KEIHOKU AKAISHICHO"},"6010542":{"prefectureJa":"京都府","cityJa":"京都市右京区","townJa":"京北田貫町","prefectureEn":"KYOTO FU","cityEn":"KYOTO SHI UKYO KU","townEn":"KEIHOKU TANUKICHO"},"6010543":{"prefectureJa":"京都府","cityJa":"京都市右京区","townJa":"京北室谷町","prefectureEn":"KYOTO FU","cityEn":"KYOTO SHI UKYO KU","townEn":"KEIHOKU SHITSUTANCHO"},"6010701":{"prefectureJa":"京都府","cityJa":"南丹市","townJa":"美山町江和","prefectureEn":"KYOTO FU","cityEn":"NANTAN SHI","townEn":"MIYAMACHO EWA"},"6010702":{"prefectureJa":"京都府","cityJa":"南丹市","townJa":"美山町田歌","prefectureEn":"KYOTO FU","cityEn":"NANTAN SHI","townEn":"MIYAMACHO TAUTA"},"6010703":{"prefectureJa":"京都府","cityJa":"南丹市","townJa":"美山町芦生","prefectureEn":"KYOTO FU","cityEn":"NANTAN SHI","townEn":"MIYAMACHO ASHIU"},"6010704":{"prefectureJa":"京都府","cityJa":"南丹市","townJa":"美山町白石","prefectureEn":"KYOTO FU","cityEn":"NANTAN SHI","townEn":"MIYAMACHO SHIRAISHI"},"6010705":{"prefectureJa":"京都府","cityJa":"南丹市","townJa":"美山町佐々里","prefectureEn":"KYOTO FU","cityEn":"NANTAN SHI","townEn":"MIYAMACHO SASARI"},"6010711":{"prefectureJa":"京都府","cityJa":"南丹市","townJa":"美山町南","prefectureEn":"KYOTO FU","cityEn":"NANTAN SHI","townEn":"MIYAMACHO MINAMI"},"6010712":{"prefectureJa":"京都府","cityJa":"南丹市","townJa":"美山町北","prefectureEn":"KYOTO FU","cityEn":"NANTAN SHI","townEn":"MIYAMACHO KITA"},"6010713":{"prefectureJa":"京都府","cityJa":"南丹市","townJa":"美山町中","prefectureEn":"KYOTO FU","cityEn":"NANTAN SHI","townEn":"MIYAMACHO NAKA"},"6010714":{"prefectureJa":"京都府","cityJa":"南丹市","townJa":"美山町河内谷","prefectureEn":"KYOTO FU","cityEn":"NANTAN SHI","townEn":"MIYAMACHO KAWAUCHIDANI"},"6010715":{"prefectureJa":"京都府","cityJa":"南丹市","townJa":"美山町下","prefectureEn":"KYOTO FU","cityEn":"NANTAN SHI","townEn":"MIYAMACHO SHIMO"},"6010716":{"prefectureJa":"京都府","cityJa":"南丹市","townJa":"美山町知見","prefectureEn":"KYOTO FU","cityEn":"NANTAN SHI","townEn":"MIYAMACHO CHIMI"},"6010721":{"prefectureJa":"京都府","cityJa":"南丹市","townJa":"美山町上平屋","prefectureEn":"KYOTO FU","cityEn":"NANTAN SHI","townEn":"MIYAMACHO KAMIHIRAYA"},"6010722":{"prefectureJa":"京都府","cityJa":"南丹市","townJa":"美山町安掛","prefectureEn":"KYOTO FU","cityEn":"NANTAN SHI","townEn":"MIYAMACHO AGAKE"},"6010723":{"prefectureJa":"京都府","cityJa":"南丹市","townJa":"美山町荒倉","prefectureEn":"KYOTO FU","cityEn":"NANTAN SHI","townEn":"MIYAMACHO ARAKURA"},"6010724":{"prefectureJa":"京都府","cityJa":"南丹市","townJa":"美山町内久保","prefectureEn":"KYOTO FU","cityEn":"NANTAN SHI","townEn":"MIYAMACHO UCHIKUBO"},"6010731":{"prefectureJa":"京都府","cityJa":"南丹市","townJa":"美山町又林","prefectureEn":"KYOTO FU","cityEn":"NANTAN SHI","townEn":"MIYAMACHO MATABAYASHI"},"6010732":{"prefectureJa":"京都府","cityJa":"南丹市","townJa":"美山町下平屋","prefectureEn":"KYOTO FU","cityEn":"NANTAN SHI","townEn":"MIYAMACHO SHIMOHIRAYA"},"6010733":{"prefectureJa":"京都府","cityJa":"南丹市","townJa":"美山町野添","prefectureEn":"KYOTO FU","cityEn":"NANTAN SHI","townEn":"MIYAMACHO NOZOE"},"6010734":{"prefectureJa":"京都府","cityJa":"南丹市","townJa":"美山町長尾","prefectureEn":"KYOTO FU","cityEn":"NANTAN SHI","townEn":"MIYAMACHO NAGAO"},"6010735":{"prefectureJa":"京都府","cityJa":"南丹市","townJa":"美山町深見","prefectureEn":"KYOTO FU","cityEn":"NANTAN SHI","townEn":"MIYAMACHO FUKAMI"},"6010741":{"prefectureJa":"京都府","cityJa":"南丹市","townJa":"美山町原","prefectureEn":"KYOTO FU","cityEn":"NANTAN SHI","townEn":"MIYAMACHO HARA"},"6010742":{"prefectureJa":"京都府","cityJa":"南丹市","townJa":"美山町板橋","prefectureEn":"KYOTO FU","cityEn":"NANTAN SHI","townEn":"MIYAMACHO ITAHASHI"},"6010743":{"prefectureJa":"京都府","cityJa":"南丹市","townJa":"美山町宮脇","prefectureEn":"KYOTO FU","cityEn":"NANTAN SHI","townEn":"MIYAMACHO MIYANOWAKI"},"6010744":{"prefectureJa":"京都府","cityJa":"南丹市","townJa":"美山町下吉田","prefectureEn":"KYOTO FU","cityEn":"NANTAN SHI","townEn":"MIYAMACHO SHIMOYOSHIDA"},"6010751":{"prefectureJa":"京都府","cityJa":"南丹市","townJa":"美山町島","prefectureEn":"KYOTO FU","cityEn":"NANTAN SHI","townEn":"MIYAMACHO SHIMA"},"6010752":{"prefectureJa":"京都府","cityJa":"南丹市","townJa":"美山町長谷","prefectureEn":"KYOTO FU","cityEn":"NANTAN SHI","townEn":"MIYAMACHO NAGATANI"},"6010753":{"prefectureJa":"京都府","cityJa":"南丹市","townJa":"美山町上司","prefectureEn":"KYOTO FU","cityEn":"NANTAN SHI","townEn":"MIYAMACHO JOSHI"},"6010754":{"prefectureJa":"京都府","cityJa":"南丹市","townJa":"美山町和泉","prefectureEn":"KYOTO FU","cityEn":"NANTAN SHI","townEn":"MIYAMACHO IZUMI"},"6010755":{"prefectureJa":"京都府","cityJa":"南丹市","townJa":"美山町静原","prefectureEn":"KYOTO FU","cityEn":"NANTAN SHI","townEn":"MIYAMACHO SHIZUHARA"},"6010761":{"prefectureJa":"京都府","cityJa":"南丹市","townJa":"美山町高野","prefectureEn":"KYOTO FU","cityEn":"NANTAN SHI","townEn":"MIYAMACHO TAKANO"},"6010762":{"prefectureJa":"京都府","cityJa":"南丹市","townJa":"美山町鶴ケ岡","prefectureEn":"KYOTO FU","cityEn":"NANTAN SHI","townEn":"MIYAMACHO TSURUGAOKA"},"6010763":{"prefectureJa":"京都府","cityJa":"南丹市","townJa":"美山町豊郷","prefectureEn":"KYOTO FU","cityEn":"NANTAN SHI","townEn":"MIYAMACHO TOYOSATO"},"6010764":{"prefectureJa":"京都府","cityJa":"南丹市","townJa":"美山町盛郷","prefectureEn":"KYOTO FU","cityEn":"NANTAN SHI","townEn":"MIYAMACHO MORISATO"},"6010765":{"prefectureJa":"京都府","cityJa":"南丹市","townJa":"美山町福居","prefectureEn":"KYOTO FU","cityEn":"NANTAN SHI","townEn":"MIYAMACHO FUKUI"},"6010771":{"prefectureJa":"京都府","cityJa":"南丹市","townJa":"美山町萱野","prefectureEn":"KYOTO FU","cityEn":"NANTAN SHI","townEn":"MIYAMACHO KAYANO"},"6010772":{"prefectureJa":"京都府","cityJa":"南丹市","townJa":"美山町大野","prefectureEn":"KYOTO FU","cityEn":"NANTAN SHI","townEn":"MIYAMACHO ONO"},"6010773":{"prefectureJa":"京都府","cityJa":"南丹市","townJa":"美山町三埜","prefectureEn":"KYOTO FU","cityEn":"NANTAN SHI","townEn":"MIYAMACHO MITSUNO"},"6010774":{"prefectureJa":"京都府","cityJa":"南丹市","townJa":"美山町肱谷","prefectureEn":"KYOTO FU","cityEn":"NANTAN SHI","townEn":"MIYAMACHO HIJITANI"},"6010775":{"prefectureJa":"京都府","cityJa":"南丹市","townJa":"美山町小渕","prefectureEn":"KYOTO FU","cityEn":"NANTAN SHI","townEn":"MIYAMACHO OBUCHI"},"6010776":{"prefectureJa":"京都府","cityJa":"南丹市","townJa":"美山町向山","prefectureEn":"KYOTO FU","cityEn":"NANTAN SHI","townEn":"MIYAMACHO MUKAIYAMA"},"6010777":{"prefectureJa":"京都府","cityJa":"南丹市","townJa":"美山町樫原","prefectureEn":"KYOTO FU","cityEn":"NANTAN SHI","townEn":"MIYAMACHO KASHIWARA"},"6010778":{"prefectureJa":"京都府","cityJa":"南丹市","townJa":"美山町音海","prefectureEn":"KYOTO FU","cityEn":"NANTAN SHI","townEn":"MIYAMACHO OTOMI"},"6011101":{"prefectureJa":"京都府","cityJa":"京都市左京区","townJa":"広河原（各町）","prefectureEn":"KYOTO FU","cityEn":"KYOTO SHI SAKYO KU","townEn":"HIROGAWARA(KAKUMACHI)"},"6011102":{"prefectureJa":"京都府","cityJa":"京都市左京区","townJa":"花脊原地町","prefectureEn":"KYOTO FU","cityEn":"KYOTO SHI SAKYO KU","townEn":"HANASE HARACHICHO"},"6011103":{"prefectureJa":"京都府","cityJa":"京都市左京区","townJa":"花脊八桝町","prefectureEn":"KYOTO FU","cityEn":"KYOTO SHI SAKYO KU","townEn":"HANASE YAMASUCHO"},"6011104":{"prefectureJa":"京都府","cityJa":"京都市左京区","townJa":"花脊大布施町","prefectureEn":"KYOTO FU","cityEn":"KYOTO SHI SAKYO KU","townEn":"HANASE OFUSECHO"},"6011105":{"prefectureJa":"京都府","cityJa":"京都市左京区","townJa":"花脊別所町","prefectureEn":"KYOTO FU","cityEn":"KYOTO SHI SAKYO KU","townEn":"HANASE BESSHOCHO"},"6011111":{"prefectureJa":"京都府","cityJa":"京都市左京区","townJa":"鞍馬本町","prefectureEn":"KYOTO FU","cityEn":"KYOTO SHI SAKYO KU","townEn":"KURAMA HOMMACHI"},"6011112":{"prefectureJa":"京都府","cityJa":"京都市左京区","townJa":"鞍馬貴船町","prefectureEn":"KYOTO FU","cityEn":"KYOTO SHI SAKYO KU","townEn":"KURAMA KIBUNECHO"},"6011113":{"prefectureJa":"京都府","cityJa":"京都市左京区","townJa":"鞍馬二ノ瀬町","prefectureEn":"KYOTO FU","cityEn":"KYOTO SHI SAKYO KU","townEn":"KURAMA NINOSECHO"},"6011121":{"prefectureJa":"京都府","cityJa":"京都市左京区","townJa":"静市静原町","prefectureEn":"KYOTO FU","cityEn":"KYOTO SHI SAKYO KU","townEn":"SHIZUICHI SHIZUHARACHO"},"6011122":{"prefectureJa":"京都府","cityJa":"京都市左京区","townJa":"静市野中町","prefectureEn":"KYOTO FU","cityEn":"KYOTO SHI SAKYO KU","townEn":"SHIZUICHI NONAKACHO"},"6011123":{"prefectureJa":"京都府","cityJa":"京都市左京区","townJa":"静市市原町","prefectureEn":"KYOTO FU","cityEn":"KYOTO SHI SAKYO KU","townEn":"SHIZUICHI ICHIHARACHO"},"6011124":{"prefectureJa":"京都府","cityJa":"京都市左京区","townJa":"岩倉上蔵町（２６７、２６８番地）","prefectureEn":"KYOTO FU","cityEn":"KYOTO SHI SAKYO KU","townEn":"IWAKURA AGURACHO(267.268-BANCHI)"},"6011125":{"prefectureJa":"京都府","cityJa":"京都市左京区","townJa":"岩倉木野町（２５１番地）","prefectureEn":"KYOTO FU","cityEn":"KYOTO SHI SAKYO KU","townEn":"IWAKURA KINOCHO(251-BANCHI)"},"6011231":{"prefectureJa":"京都府","cityJa":"京都市左京区","townJa":"大原尾越町","prefectureEn":"KYOTO FU","cityEn":"KYOTO SHI SAKYO KU","townEn":"OHARA OGOSECHO"},"6011232":{"prefectureJa":"京都府","cityJa":"京都市左京区","townJa":"大原大見町","prefectureEn":"KYOTO FU","cityEn":"KYOTO SHI SAKYO KU","townEn":"OHARA OMICHO"},"6011233":{"prefectureJa":"京都府","cityJa":"京都市左京区","townJa":"大原百井町","prefectureEn":"KYOTO FU","cityEn":"KYOTO SHI SAKYO KU","townEn":"OHARA MOMOICHO"},"6011234":{"prefectureJa":"京都府","cityJa":"京都市左京区","townJa":"大原小出石町","prefectureEn":"KYOTO FU","cityEn":"KYOTO SHI SAKYO KU","townEn":"OHARA KODEISHICHO"},"6011235":{"prefectureJa":"京都府","cityJa":"京都市左京区","townJa":"大原古知平町","prefectureEn":"KYOTO FU","cityEn":"KYOTO SHI SAKYO KU","townEn":"OHARA KOCHIHIRACHO"},"6011241":{"prefectureJa":"京都府","cityJa":"京都市左京区","townJa":"大原勝林院町","prefectureEn":"KYOTO FU","cityEn":"KYOTO SHI SAKYO KU","townEn":"OHARA SHORININCHO"},"6011242":{"prefectureJa":"京都府","cityJa":"京都市左京区","townJa":"大原来迎院町","prefectureEn":"KYOTO FU","cityEn":"KYOTO SHI SAKYO KU","townEn":"OHARA RAIKOINCHO"},"6011243":{"prefectureJa":"京都府","cityJa":"京都市左京区","townJa":"大原大長瀬町","prefectureEn":"KYOTO FU","cityEn":"KYOTO SHI SAKYO KU","townEn":"OHARA ONAGASECHO"},"6011244":{"prefectureJa":"京都府","cityJa":"京都市左京区","townJa":"大原上野町","prefectureEn":"KYOTO FU","cityEn":"KYOTO SHI SAKYO KU","townEn":"OHARA UENOCHO"},"6011245":{"prefectureJa":"京都府","cityJa":"京都市左京区","townJa":"大原戸寺町","prefectureEn":"KYOTO FU","cityEn":"KYOTO SHI SAKYO KU","townEn":"OHARA TODERACHO"},"6011246":{"prefectureJa":"京都府","cityJa":"京都市左京区","townJa":"大原井出町","prefectureEn":"KYOTO FU","cityEn":"KYOTO SHI SAKYO KU","townEn":"OHARA IDECHO"},"6011247":{"prefectureJa":"京都府","cityJa":"京都市左京区","townJa":"大原野村町","prefectureEn":"KYOTO FU","cityEn":"KYOTO SHI SAKYO KU","townEn":"OHARA NOMURACHO"},"6011248":{"prefectureJa":"京都府","cityJa":"京都市左京区","townJa":"大原草生町","prefectureEn":"KYOTO FU","cityEn":"KYOTO SHI SAKYO KU","townEn":"OHARA KUSAOCHO"},"6011251":{"prefectureJa":"京都府","cityJa":"京都市左京区","townJa":"八瀬花尻町","prefectureEn":"KYOTO FU","cityEn":"KYOTO SHI SAKYO KU","townEn":"YASE HANAJIRICHO"},"6011252":{"prefectureJa":"京都府","cityJa":"京都市左京区","townJa":"八瀬秋元町","prefectureEn":"KYOTO FU","cityEn":"KYOTO SHI SAKYO KU","townEn":"YASE AKIMOTOCHO"},"6011253":{"prefectureJa":"京都府","cityJa":"京都市左京区","townJa":"八瀬近衛町","prefectureEn":"KYOTO FU","cityEn":"KYOTO SHI SAKYO KU","townEn":"YASE KONOECHO"},"6011254":{"prefectureJa":"京都府","cityJa":"京都市左京区","townJa":"八瀬野瀬町（その他）","prefectureEn":"KYOTO FU","cityEn":"KYOTO SHI SAKYO KU","townEn":"YASENOSECHO(SONOTA)"},"6011255":{"prefectureJa":"京都府","cityJa":"京都市左京区","townJa":"上高野東山（５５、５７－６、６４、６５、７１－１、７１－２１、","prefectureEn":"KYOTO FU","cityEn":"KYOTO SHI SAKYO KU","townEn":"72.189.189-1-BANCHI)"},"6011301":{"prefectureJa":"京都府","cityJa":"京都市伏見区","townJa":"醍醐上山田","prefectureEn":"KYOTO FU","cityEn":"KYOTO SHI FUSHIMI KU","townEn":"DAIGO KAMIYAMADA"},"6011302":{"prefectureJa":"京都府","cityJa":"京都市伏見区","townJa":"醍醐内ケ井戸","prefectureEn":"KYOTO FU","cityEn":"KYOTO SHI FUSHIMI KU","townEn":"DAIGO UCHIGAIDO"},"6011303":{"prefectureJa":"京都府","cityJa":"京都市伏見区","townJa":"醍醐大畑町","prefectureEn":"KYOTO FU","cityEn":"KYOTO SHI FUSHIMI KU","townEn":"DAIGO OHATACHO"},"6011304":{"prefectureJa":"京都府","cityJa":"京都市伏見区","townJa":"醍醐山ケ鼻","prefectureEn":"KYOTO FU","cityEn":"KYOTO SHI FUSHIMI KU","townEn":"DAIGO YAMAGAHANA"},"6011305":{"prefectureJa":"京都府","cityJa":"京都市伏見区","townJa":"醍醐柿原町","prefectureEn":"KYOTO FU","cityEn":"KYOTO SHI FUSHIMI KU","townEn":"DAIGO KAKIHARACHO"},"6011306":{"prefectureJa":"京都府","cityJa":"京都市伏見区","townJa":"醍醐連蔵","prefectureEn":"KYOTO FU","cityEn":"KYOTO SHI FUSHIMI KU","townEn":"DAIGO RENZO"},"6011307":{"prefectureJa":"京都府","cityJa":"京都市伏見区","townJa":"醍醐狭間","prefectureEn":"KYOTO FU","cityEn":"KYOTO SHI FUSHIMI KU","townEn":"DAIGO HAZAMA"},"6011308":{"prefectureJa":"京都府","cityJa":"京都市伏見区","townJa":"醍醐御所ノ内","prefectureEn":"KYOTO FU","cityEn":"KYOTO SHI FUSHIMI KU","townEn":"DAIGO GOSHONOCHI"},"6011311":{"prefectureJa":"京都府","cityJa":"京都市伏見区","townJa":"醍醐大高町","prefectureEn":"KYOTO FU","cityEn":"KYOTO SHI FUSHIMI KU","townEn":"DAIGO OTAKACHO"},"6011312":{"prefectureJa":"京都府","cityJa":"京都市伏見区","townJa":"醍醐片山町","prefectureEn":"KYOTO FU","cityEn":"KYOTO SHI FUSHIMI KU","townEn":"DAIGO KATAYAMACHO"},"6011313":{"prefectureJa":"京都府","cityJa":"京都市伏見区","townJa":"醍醐御陵東裏町","prefectureEn":"KYOTO FU","cityEn":"KYOTO SHI FUSHIMI KU","townEn":"DAIGO GORYOHIGASHIURACHO"},"6011314":{"prefectureJa":"京都府","cityJa":"京都市伏見区","townJa":"醍醐御陵西裏町","prefectureEn":"KYOTO FU","cityEn":"KYOTO SHI FUSHIMI KU","townEn":"DAIGO GORYONISHIURACHO"},"6011315":{"prefectureJa":"京都府","cityJa":"京都市伏見区","townJa":"醍醐烏橋町","prefectureEn":"KYOTO FU","cityEn":"KYOTO SHI FUSHIMI KU","townEn":"DAIGO KARASUBASHICHO"},"6011316":{"prefectureJa":"京都府","cityJa":"京都市伏見区","townJa":"醍醐古道町","prefectureEn":"KYOTO FU","cityEn":"KYOTO SHI FUSHIMI KU","townEn":"DAIGO FURUMICHICHO"},"6011317":{"prefectureJa":"京都府","cityJa":"京都市伏見区","townJa":"醍醐京道町","prefectureEn":"KYOTO FU","cityEn":"KYOTO SHI FUSHIMI KU","townEn":"DAIGO KYOMICHICHO"},"6011318":{"prefectureJa":"京都府","cityJa":"京都市伏見区","townJa":"醍醐廻り戸町","prefectureEn":"KYOTO FU","cityEn":"KYOTO SHI FUSHIMI KU","townEn":"DAIGO MAWARIDOCHO"},"6011321":{"prefectureJa":"京都府","cityJa":"京都市伏見区","townJa":"醍醐北端山","prefectureEn":"KYOTO FU","cityEn":"KYOTO SHI FUSHIMI KU","townEn":"DAIGO KITAHAYAMA"},"6011322":{"prefectureJa":"京都府","cityJa":"京都市伏見区","townJa":"醍醐北伽藍町","prefectureEn":"KYOTO FU","cityEn":"KYOTO SHI FUSHIMI KU","townEn":"DAIGO KITAGARANCHO"},"6011323":{"prefectureJa":"京都府","cityJa":"京都市伏見区","townJa":"醍醐赤間南裏町","prefectureEn":"KYOTO FU","cityEn":"KYOTO SHI FUSHIMI KU","townEn":"DAIGO AKAMAMINAMIURACHO"},"6011324":{"prefectureJa":"京都府","cityJa":"京都市伏見区","townJa":"醍醐伽藍町","prefectureEn":"KYOTO FU","cityEn":"KYOTO SHI FUSHIMI KU","townEn":"DAIGO GARANCHO"},"6011325":{"prefectureJa":"京都府","cityJa":"京都市伏見区","townJa":"醍醐東大路町","prefectureEn":"KYOTO FU","cityEn":"KYOTO SHI FUSHIMI KU","townEn":"DAIGO HIGASHIOJICHO"},"6011326":{"prefectureJa":"京都府","cityJa":"京都市伏見区","townJa":"醍醐新町裏町","prefectureEn":"KYOTO FU","cityEn":"KYOTO SHI FUSHIMI KU","townEn":"DAIGO SHIMMACHIURAMACHI"},"6011327":{"prefectureJa":"京都府","cityJa":"京都市伏見区","townJa":"醍醐切レ戸町","prefectureEn":"KYOTO FU","cityEn":"KYOTO SHI FUSHIMI KU","townEn":"DAIGO KIREDOCHO"},"6011331":{"prefectureJa":"京都府","cityJa":"京都市伏見区","townJa":"醍醐南端山町","prefectureEn":"KYOTO FU","cityEn":"KYOTO SHI FUSHIMI KU","townEn":"DAIGO MINAMIHAYAMACHO"},"6011332":{"prefectureJa":"京都府","cityJa":"京都市伏見区","townJa":"醍醐下端山町","prefectureEn":"KYOTO FU","cityEn":"KYOTO SHI FUSHIMI KU","townEn":"DAIGO SHIMOHAYAMACHO"},"6011333":{"prefectureJa":"京都府","cityJa":"京都市伏見区","townJa":"醍醐上端山町","prefectureEn":"KYOTO FU","cityEn":"KYOTO SHI FUSHIMI KU","townEn":"DAIGO KAMIHAYAMACHO"},"6011334":{"prefectureJa":"京都府","cityJa":"京都市伏見区","townJa":"醍醐勝口町","prefectureEn":"KYOTO FU","cityEn":"KYOTO SHI FUSHIMI KU","townEn":"DAIGO SHOKUCHICHO"},"6011335":{"prefectureJa":"京都府","cityJa":"京都市伏見区","townJa":"醍醐一言寺裏町","prefectureEn":"KYOTO FU","cityEn":"KYOTO SHI FUSHIMI KU","townEn":"DAIGO ICHIGONJIURACHO"},"6011336":{"prefectureJa":"京都府","cityJa":"京都市伏見区","townJa":"醍醐柏森町","prefectureEn":"KYOTO FU","cityEn":"KYOTO SHI FUSHIMI KU","townEn":"DAIGO KASHIWAMORICHO"},"6011337":{"prefectureJa":"京都府","cityJa":"京都市伏見区","townJa":"醍醐槇ノ内町","prefectureEn":"KYOTO FU","cityEn":"KYOTO SHI FUSHIMI KU","townEn":"DAIGO MAKINOCHICHO"},"6011338":{"prefectureJa":"京都府","cityJa":"京都市伏見区","townJa":"醍醐落保町","prefectureEn":"KYOTO FU","cityEn":"KYOTO SHI FUSHIMI KU","townEn":"DAIGO OCHIBOCHO"},"6011341":{"prefectureJa":"京都府","cityJa":"京都市伏見区","townJa":"醍醐岸ノ上町","prefectureEn":"KYOTO FU","cityEn":"KYOTO SHI FUSHIMI KU","townEn":"DAIGO KISHINOECHO"},"6011342":{"prefectureJa":"京都府","cityJa":"京都市伏見区","townJa":"醍醐上山口町","prefectureEn":"KYOTO FU","cityEn":"KYOTO SHI FUSHIMI KU","townEn":"DAIGO KAMIYAMAGUCHICHO"},"6011343":{"prefectureJa":"京都府","cityJa":"京都市伏見区","townJa":"醍醐下山口町","prefectureEn":"KYOTO FU","cityEn":"KYOTO SHI FUSHIMI KU","townEn":"DAIGO SHIMOYAMAGUCHICHO"},"6011344":{"prefectureJa":"京都府","cityJa":"京都市伏見区","townJa":"醍醐辰巳町","prefectureEn":"KYOTO FU","cityEn":"KYOTO SHI FUSHIMI KU","townEn":"DAIGO TATSUMICHO"},"6011345":{"prefectureJa":"京都府","cityJa":"京都市伏見区","townJa":"醍醐外山街道町","prefectureEn":"KYOTO FU","cityEn":"KYOTO SHI FUSHIMI KU","townEn":"DAIGO SOTOYAMAKAIDOCHO"},"6011346":{"prefectureJa":"京都府","cityJa":"京都市伏見区","townJa":"醍醐東合場町","prefectureEn":"KYOTO FU","cityEn":"KYOTO SHI FUSHIMI KU","townEn":"DAIGO HIGASHIAIBACHO"},"6011347":{"prefectureJa":"京都府","cityJa":"京都市伏見区","townJa":"醍醐合場町","prefectureEn":"KYOTO FU","cityEn":"KYOTO SHI FUSHIMI KU","townEn":"DAIGO AIBACHO"},"6011351":{"prefectureJa":"京都府","cityJa":"京都市伏見区","townJa":"醍醐和泉町","prefectureEn":"KYOTO FU","cityEn":"KYOTO SHI FUSHIMI KU","townEn":"DAIGO IZUMICHO"},"6011352":{"prefectureJa":"京都府","cityJa":"京都市伏見区","townJa":"醍醐南里町","prefectureEn":"KYOTO FU","cityEn":"KYOTO SHI FUSHIMI KU","townEn":"DAIGO MINAMISATOCHO"},"6011353":{"prefectureJa":"京都府","cityJa":"京都市伏見区","townJa":"醍醐御園尾町","prefectureEn":"KYOTO FU","cityEn":"KYOTO SHI FUSHIMI KU","townEn":"DAIGO MISONOCHO"},"6011354":{"prefectureJa":"京都府","cityJa":"京都市伏見区","townJa":"醍醐構口町","prefectureEn":"KYOTO FU","cityEn":"KYOTO SHI FUSHIMI KU","townEn":"DAIGO KAMAEGUCHICHO"},"6011355":{"prefectureJa":"京都府","cityJa":"京都市伏見区","townJa":"醍醐多近田町","prefectureEn":"KYOTO FU","cityEn":"KYOTO SHI FUSHIMI KU","townEn":"DAIGO TAKONDACHO"},"6011356":{"prefectureJa":"京都府","cityJa":"京都市伏見区","townJa":"醍醐南西裏町","prefectureEn":"KYOTO FU","cityEn":"KYOTO SHI FUSHIMI KU","townEn":"DAIGO MINAMINISHIURACHO"},"6011357":{"prefectureJa":"京都府","cityJa":"京都市伏見区","townJa":"醍醐僧尊坊町","prefectureEn":"KYOTO FU","cityEn":"KYOTO SHI FUSHIMI KU","townEn":"DAIGO DODOMBOCHO"},"6011361":{"prefectureJa":"京都府","cityJa":"京都市伏見区","townJa":"醍醐御霊ケ下町","prefectureEn":"KYOTO FU","cityEn":"KYOTO SHI FUSHIMI KU","townEn":"DAIGO GORYOGASHITACHO"},"6011362":{"prefectureJa":"京都府","cityJa":"京都市伏見区","townJa":"醍醐池田町","prefectureEn":"KYOTO FU","cityEn":"KYOTO SHI FUSHIMI KU","townEn":"DAIGO IKEDACHO"},"6011363":{"prefectureJa":"京都府","cityJa":"京都市伏見区","townJa":"醍醐鍵尾町","prefectureEn":"KYOTO FU","cityEn":"KYOTO SHI FUSHIMI KU","townEn":"DAIGO KAGIOCHO"},"6011364":{"prefectureJa":"京都府","cityJa":"京都市伏見区","townJa":"醍醐江奈志町","prefectureEn":"KYOTO FU","cityEn":"KYOTO SHI FUSHIMI KU","townEn":"DAIGO ENASHICHO"},"6011365":{"prefectureJa":"京都府","cityJa":"京都市伏見区","townJa":"醍醐新開","prefectureEn":"KYOTO FU","cityEn":"KYOTO SHI FUSHIMI KU","townEn":"DAIGO SHINKAI"},"6011366":{"prefectureJa":"京都府","cityJa":"京都市伏見区","townJa":"醍醐大構町","prefectureEn":"KYOTO FU","cityEn":"KYOTO SHI FUSHIMI KU","townEn":"DAIGO OKAMAECHO"},"6011371":{"prefectureJa":"京都府","cityJa":"京都市伏見区","townJa":"醍醐上ノ山町","prefectureEn":"KYOTO FU","cityEn":"KYOTO SHI FUSHIMI KU","townEn":"DAIGO UENOYAMACHO"},"6011372":{"prefectureJa":"京都府","cityJa":"京都市伏見区","townJa":"醍醐平松町","prefectureEn":"KYOTO FU","cityEn":"KYOTO SHI FUSHIMI KU","townEn":"DAIGO HIRAMATSUCHO"},"6011373":{"prefectureJa":"京都府","cityJa":"京都市伏見区","townJa":"醍醐中山町","prefectureEn":"KYOTO FU","cityEn":"KYOTO SHI FUSHIMI KU","townEn":"DAIGO NAKAYAMACHO"},"6011374":{"prefectureJa":"京都府","cityJa":"京都市伏見区","townJa":"醍醐西大路町","prefectureEn":"KYOTO FU","cityEn":"KYOTO SHI FUSHIMI KU","townEn":"DAIGO NISHIOJICHO"},"6011375":{"prefectureJa":"京都府","cityJa":"京都市伏見区","townJa":"醍醐高畑町","prefectureEn":"KYOTO FU","cityEn":"KYOTO SHI FUSHIMI KU","townEn":"DAIGO TAKAHATACHO"},"6011376":{"prefectureJa":"京都府","cityJa":"京都市伏見区","townJa":"醍醐折戸町","prefectureEn":"KYOTO FU","cityEn":"KYOTO SHI FUSHIMI KU","townEn":"DAIGO ORIDOCHO"},"6011377":{"prefectureJa":"京都府","cityJa":"京都市伏見区","townJa":"醍醐北西裏町","prefectureEn":"KYOTO FU","cityEn":"KYOTO SHI FUSHIMI KU","townEn":"DAIGO KITANISHIURACHO"},"6011378":{"prefectureJa":"京都府","cityJa":"京都市伏見区","townJa":"醍醐川久保町","prefectureEn":"KYOTO FU","cityEn":"KYOTO SHI FUSHIMI KU","townEn":"DAIGO KAWAKUBOCHO"},"6011381":{"prefectureJa":"京都府","cityJa":"京都市伏見区","townJa":"醍醐北谷","prefectureEn":"KYOTO FU","cityEn":"KYOTO SHI FUSHIMI KU","townEn":"DAIGO KITADANI"},"6011382":{"prefectureJa":"京都府","cityJa":"京都市伏見区","townJa":"醍醐南谷","prefectureEn":"KYOTO FU","cityEn":"KYOTO SHI FUSHIMI KU","townEn":"DAIGO MINAMIDANI"},"6011383":{"prefectureJa":"京都府","cityJa":"京都市伏見区","townJa":"醍醐醍醐山","prefectureEn":"KYOTO FU","cityEn":"KYOTO SHI FUSHIMI KU","townEn":"DAIGO DAIGOYAMA"},"6011384":{"prefectureJa":"京都府","cityJa":"京都市伏見区","townJa":"醍醐高田","prefectureEn":"KYOTO FU","cityEn":"KYOTO SHI FUSHIMI KU","townEn":"DAIGO TAKADA"},"6011385":{"prefectureJa":"京都府","cityJa":"京都市伏見区","townJa":"醍醐宮ノ下町","prefectureEn":"KYOTO FU","cityEn":"KYOTO SHI FUSHIMI KU","townEn":"DAIGO MIYANOSHITACHO"},"6011386":{"prefectureJa":"京都府","cityJa":"京都市伏見区","townJa":"醍醐陀羅谷","prefectureEn":"KYOTO FU","cityEn":"KYOTO SHI FUSHIMI KU","townEn":"DAIGO DARATANI"},"6011387":{"prefectureJa":"京都府","cityJa":"京都市伏見区","townJa":"醍醐一ノ切町","prefectureEn":"KYOTO FU","cityEn":"KYOTO SHI FUSHIMI KU","townEn":"DAIGO NINOKIRICHO"},"6011391":{"prefectureJa":"京都府","cityJa":"宇治市","townJa":"東笠取","prefectureEn":"KYOTO FU","cityEn":"UJI SHI","townEn":"HIGASHIKASATORI"},"6011392":{"prefectureJa":"京都府","cityJa":"宇治市","townJa":"西笠取","prefectureEn":"KYOTO FU","cityEn":"UJI SHI","townEn":"NISHIKASATORI"},"6011393":{"prefectureJa":"京都府","cityJa":"宇治市","townJa":"二尾","prefectureEn":"KYOTO FU","cityEn":"UJI SHI","townEn":"NIO"},"6011394":{"prefectureJa":"京都府","cityJa":"宇治市","townJa":"池尾","prefectureEn":"KYOTO FU","cityEn":"UJI SHI","townEn":"IKENO"},"6011395":{"prefectureJa":"京都府","cityJa":"宇治市","townJa":"炭山","prefectureEn":"KYOTO FU","cityEn":"UJI SHI","townEn":"SUMIYAMA"},"6011396":{"prefectureJa":"京都府","cityJa":"宇治市","townJa":"莵道東垣内","prefectureEn":"KYOTO FU","cityEn":"UJI SHI","townEn":"TODO HIGASHIGAITO"},"6011401":{"prefectureJa":"京都府","cityJa":"京都市伏見区","townJa":"日野北山","prefectureEn":"KYOTO FU","cityEn":"KYOTO SHI FUSHIMI KU","townEn":"HINO KITAYAMA"},"6011402":{"prefectureJa":"京都府","cityJa":"京都市伏見区","townJa":"日野南山","prefectureEn":"KYOTO FU","cityEn":"KYOTO SHI FUSHIMI KU","townEn":"HINO MINAMIYAMA"},"6011403":{"prefectureJa":"京都府","cityJa":"京都市伏見区","townJa":"日野船尾","prefectureEn":"KYOTO FU","cityEn":"KYOTO SHI FUSHIMI KU","townEn":"HINO FUNAO"},"6011404":{"prefectureJa":"京都府","cityJa":"京都市伏見区","townJa":"日野北川頬","prefectureEn":"KYOTO FU","cityEn":"KYOTO SHI FUSHIMI KU","townEn":"HINO KITAKAWAZURA"},"6011405":{"prefectureJa":"京都府","cityJa":"京都市伏見区","townJa":"日野林","prefectureEn":"KYOTO FU","cityEn":"KYOTO SHI FUSHIMI KU","townEn":"HINO HAYASHI"},"6011406":{"prefectureJa":"京都府","cityJa":"京都市伏見区","townJa":"日野谷寺町","prefectureEn":"KYOTO FU","cityEn":"KYOTO SHI FUSHIMI KU","townEn":"HINO TANIDERACHO"},"6011411":{"prefectureJa":"京都府","cityJa":"京都市伏見区","townJa":"日野慈悲町","prefectureEn":"KYOTO FU","cityEn":"KYOTO SHI FUSHIMI KU","townEn":"HINO JIHICHO"},"6011412":{"prefectureJa":"京都府","cityJa":"京都市伏見区","townJa":"日野畑出町","prefectureEn":"KYOTO FU","cityEn":"KYOTO SHI FUSHIMI KU","townEn":"HINO HATADECHO"},"6011413":{"prefectureJa":"京都府","cityJa":"京都市伏見区","townJa":"日野谷田町","prefectureEn":"KYOTO FU","cityEn":"KYOTO SHI FUSHIMI KU","townEn":"HINO TANIDACHO"},"6011414":{"prefectureJa":"京都府","cityJa":"京都市伏見区","townJa":"日野奥出","prefectureEn":"KYOTO FU","cityEn":"KYOTO SHI FUSHIMI KU","townEn":"HINO OKUDE"},"6011415":{"prefectureJa":"京都府","cityJa":"京都市伏見区","townJa":"日野野色町","prefectureEn":"KYOTO FU","cityEn":"KYOTO SHI FUSHIMI KU","townEn":"HINO NOIROCHO"},"6011416":{"prefectureJa":"京都府","cityJa":"京都市伏見区","townJa":"日野岡西町","prefectureEn":"KYOTO FU","cityEn":"KYOTO SHI FUSHIMI KU","townEn":"HINO OKANISHICHO"},"6011417":{"prefectureJa":"京都府","cityJa":"京都市伏見区","townJa":"日野西大道町","prefectureEn":"KYOTO FU","cityEn":"KYOTO SHI FUSHIMI KU","townEn":"HINO NISHIDAIDOCHO"},"6011421":{"prefectureJa":"京都府","cityJa":"京都市伏見区","townJa":"日野馬場出町","prefectureEn":"KYOTO FU","cityEn":"KYOTO SHI FUSHIMI KU","townEn":"HINO BAMBATECHO"},"6011422":{"prefectureJa":"京都府","cityJa":"京都市伏見区","townJa":"日野不動講町","prefectureEn":"KYOTO FU","cityEn":"KYOTO SHI FUSHIMI KU","townEn":"HINO FUDOKOCHO"},"6011423":{"prefectureJa":"京都府","cityJa":"京都市伏見区","townJa":"日野西風呂町","prefectureEn":"KYOTO FU","cityEn":"KYOTO SHI FUSHIMI KU","townEn":"HINO NISHIFUROCHO"},"6011424":{"prefectureJa":"京都府","cityJa":"京都市伏見区","townJa":"日野田頬町","prefectureEn":"KYOTO FU","cityEn":"KYOTO SHI FUSHIMI KU","townEn":"HINO TAZURACHO"},"6011425":{"prefectureJa":"京都府","cityJa":"京都市伏見区","townJa":"日野田中町","prefectureEn":"KYOTO FU","cityEn":"KYOTO SHI FUSHIMI KU","townEn":"HINO TANAKACHO"},"6011426":{"prefectureJa":"京都府","cityJa":"京都市伏見区","townJa":"日野西川頬","prefectureEn":"KYOTO FU","cityEn":"KYOTO SHI FUSHIMI KU","townEn":"HINO NISHIKAWAZURA"},"6011431":{"prefectureJa":"京都府","cityJa":"京都市伏見区","townJa":"石田大受町","prefectureEn":"KYOTO FU","cityEn":"KYOTO SHI FUSHIMI KU","townEn":"ISHIDA OUKECHO"},"6011432":{"prefectureJa":"京都府","cityJa":"京都市伏見区","townJa":"石田内里町","prefectureEn":"KYOTO FU","cityEn":"KYOTO SHI FUSHIMI KU","townEn":"ISHIDA UCHISATOCHO"},"6011433":{"prefectureJa":"京都府","cityJa":"京都市伏見区","townJa":"石田大山町","prefectureEn":"KYOTO FU","cityEn":"KYOTO SHI FUSHIMI KU","townEn":"ISHIDA OYAMACHO"},"6011434":{"prefectureJa":"京都府","cityJa":"京都市伏見区","townJa":"石田森南町","prefectureEn":"KYOTO FU","cityEn":"KYOTO SHI FUSHIMI KU","townEn":"ISHIDA MORIMINAMICHO"},"6011435":{"prefectureJa":"京都府","cityJa":"京都市伏見区","townJa":"石田桜木","prefectureEn":"KYOTO FU","cityEn":"KYOTO SHI FUSHIMI KU","townEn":"ISHIDA SAKURAGI"},"6011436":{"prefectureJa":"京都府","cityJa":"京都市伏見区","townJa":"石田西ノ坪","prefectureEn":"KYOTO FU","cityEn":"KYOTO SHI FUSHIMI KU","townEn":"ISHIDA NISHINOTSUBO"},"6011437":{"prefectureJa":"京都府","cityJa":"京都市伏見区","townJa":"石田森西","prefectureEn":"KYOTO FU","cityEn":"KYOTO SHI FUSHIMI KU","townEn":"ISHIDA MORINISHI"},"6011438":{"prefectureJa":"京都府","cityJa":"京都市伏見区","townJa":"石田川向","prefectureEn":"KYOTO FU","cityEn":"KYOTO SHI FUSHIMI KU","townEn":"ISHIDA KAWAMUKAI"},"6011439":{"prefectureJa":"京都府","cityJa":"京都市伏見区","townJa":"石田森東町","prefectureEn":"KYOTO FU","cityEn":"KYOTO SHI FUSHIMI KU","townEn":"ISHIDA MORIHIGASHICHO"},"6011441":{"prefectureJa":"京都府","cityJa":"京都市伏見区","townJa":"小栗栖北谷町","prefectureEn":"KYOTO FU","cityEn":"KYOTO SHI FUSHIMI KU","townEn":"OGURISU KITADANICHO"},"6011442":{"prefectureJa":"京都府","cityJa":"京都市伏見区","townJa":"小栗栖丸山","prefectureEn":"KYOTO FU","cityEn":"KYOTO SHI FUSHIMI KU","townEn":"OGURISU MARUYAMA"},"6011443":{"prefectureJa":"京都府","cityJa":"京都市伏見区","townJa":"小栗栖岩ケ淵町","prefectureEn":"KYOTO FU","cityEn":"KYOTO SHI FUSHIMI KU","townEn":"OGURISU IWAGAFUCHICHO"},"6011444":{"prefectureJa":"京都府","cityJa":"京都市伏見区","townJa":"小栗栖牛ケ淵町","prefectureEn":"KYOTO FU","cityEn":"KYOTO SHI FUSHIMI KU","townEn":"OGURISU USHIGAFUCHICHO"},"6011445":{"prefectureJa":"京都府","cityJa":"京都市伏見区","townJa":"小栗栖森ケ淵町","prefectureEn":"KYOTO FU","cityEn":"KYOTO SHI FUSHIMI KU","townEn":"OGURISU MORIGAFUCHICHO"},"6011446":{"prefectureJa":"京都府","cityJa":"京都市伏見区","townJa":"小栗栖北後藤町","prefectureEn":"KYOTO FU","cityEn":"KYOTO SHI FUSHIMI KU","townEn":"OGURISU KITAGOTOCHO"},"6011451":{"prefectureJa":"京都府","cityJa":"京都市伏見区","townJa":"小栗栖鉢伏","prefectureEn":"KYOTO FU","cityEn":"KYOTO SHI FUSHIMI KU","townEn":"OGURISU HACHIFUSE"},"6011452":{"prefectureJa":"京都府","cityJa":"京都市伏見区","townJa":"小栗栖西ノ峯","prefectureEn":"KYOTO FU","cityEn":"KYOTO SHI FUSHIMI KU","townEn":"OGURISU NISHINOMINE"},"6011453":{"prefectureJa":"京都府","cityJa":"京都市伏見区","townJa":"小栗栖西谷町","prefectureEn":"KYOTO FU","cityEn":"KYOTO SHI FUSHIMI KU","townEn":"OGURISU NISHIDANICHO"},"6011454":{"prefectureJa":"京都府","cityJa":"京都市伏見区","townJa":"小栗栖山口町","prefectureEn":"KYOTO FU","cityEn":"KYOTO SHI FUSHIMI KU","townEn":"OGURISU YAMAGUCHICHO"},"6011455":{"prefectureJa":"京都府","cityJa":"京都市伏見区","townJa":"小栗栖小阪町","prefectureEn":"KYOTO FU","cityEn":"KYOTO SHI FUSHIMI KU","townEn":"OGURISU KOSAKACHO"},"6011456":{"prefectureJa":"京都府","cityJa":"京都市伏見区","townJa":"小栗栖南後藤町","prefectureEn":"KYOTO FU","cityEn":"KYOTO SHI FUSHIMI KU","townEn":"OGURISU MINAMIGOTOCHO"},"6011461":{"prefectureJa":"京都府","cityJa":"京都市伏見区","townJa":"小栗栖宮山","prefectureEn":"KYOTO FU","cityEn":"KYOTO SHI FUSHIMI KU","townEn":"OGURISU MIYAYAMA"},"6011462":{"prefectureJa":"京都府","cityJa":"京都市伏見区","townJa":"小栗栖森本町","prefectureEn":"KYOTO FU","cityEn":"KYOTO SHI FUSHIMI KU","townEn":"OGURISU MORIMOTOCHO"},"6011463":{"prefectureJa":"京都府","cityJa":"京都市伏見区","townJa":"小栗栖中山田町","prefectureEn":"KYOTO FU","cityEn":"KYOTO SHI FUSHIMI KU","townEn":"OGURISU NAKAYAMADACHO"},"6011464":{"prefectureJa":"京都府","cityJa":"京都市伏見区","townJa":"小栗栖石川町","prefectureEn":"KYOTO FU","cityEn":"KYOTO SHI FUSHIMI KU","townEn":"OGURISU ISHIKAWACHO"},"6018001":{"prefectureJa":"京都府","cityJa":"京都市南区","townJa":"東九条室町","prefectureEn":"KYOTO FU","cityEn":"KYOTO SHI MINAMI KU","townEn":"HIGASHIKUJO MUROMACHI"},"6018002":{"prefectureJa":"京都府","cityJa":"京都市南区","townJa":"東九条上殿田町","prefectureEn":"KYOTO FU","cityEn":"KYOTO SHI MINAMI KU","townEn":"HIGASHIKUJO KAMITONODACHO"},"6018003":{"prefectureJa":"京都府","cityJa":"京都市南区","townJa":"東九条西山王町","prefectureEn":"KYOTO FU","cityEn":"KYOTO SHI MINAMI KU","townEn":"HIGASHIKUJO NISHISANNOCHO"},"6018004":{"prefectureJa":"京都府","cityJa":"京都市南区","townJa":"東九条東山王町","prefectureEn":"KYOTO FU","cityEn":"KYOTO SHI MINAMI KU","townEn":"HIGASHIKUJO HIGASHISANNOCHO"},"6018005":{"prefectureJa":"京都府","cityJa":"京都市南区","townJa":"東九条西岩本町","prefectureEn":"KYOTO FU","cityEn":"KYOTO SHI MINAMI KU","townEn":"HIGASHIKUJO NISHIIWAMOTOCHO"},"6018006":{"prefectureJa":"京都府","cityJa":"京都市南区","townJa":"東九条東岩本町","prefectureEn":"KYOTO FU","cityEn":"KYOTO SHI MINAMI KU","townEn":"HIGASHIKUJO HIGASHIIWAMOTOCHO"},"6018007":{"prefectureJa":"京都府","cityJa":"京都市南区","townJa":"東九条北河原町","prefectureEn":"KYOTO FU","cityEn":"KYOTO SHI MINAMI KU","townEn":"HIGASHIKUJO KITAKAWARAMACHI"},"6018011":{"prefectureJa":"京都府","cityJa":"京都市南区","townJa":"東九条南山王町","prefectureEn":"KYOTO FU","cityEn":"KYOTO SHI MINAMI KU","townEn":"HIGASHIKUJO MINAMISANNOCHO"},"6018012":{"prefectureJa":"京都府","cityJa":"京都市南区","townJa":"東九条南岩本町","prefectureEn":"KYOTO FU","cityEn":"KYOTO SHI MINAMI KU","townEn":"HIGASHIKUJO MINAMIIWAMOTOCHO"},"6018013":{"prefectureJa":"京都府","cityJa":"京都市南区","townJa":"東九条南河原町","prefectureEn":"KYOTO FU","cityEn":"KYOTO SHI MINAMI KU","townEn":"HIGASHIKUJO MINAMIKAWARAMACHI"},"6018014":{"prefectureJa":"京都府","cityJa":"京都市南区","townJa":"東九条河西町","prefectureEn":"KYOTO FU","cityEn":"KYOTO SHI MINAMI KU","townEn":"HIGASHIKUJO KAWANISHICHO"},"6018015":{"prefectureJa":"京都府","cityJa":"京都市南区","townJa":"東九条上御霊町","prefectureEn":"KYOTO FU","cityEn":"KYOTO SHI MINAMI KU","townEn":"HIGASHIKUJO KAMIGORYOCHO"},"6018016":{"prefectureJa":"京都府","cityJa":"京都市南区","townJa":"東九条烏丸町","prefectureEn":"KYOTO FU","cityEn":"KYOTO SHI MINAMI KU","townEn":"HIGASHIKUJO KARASUMACHO"},"6018017":{"prefectureJa":"京都府","cityJa":"京都市南区","townJa":"東九条北烏丸町","prefectureEn":"KYOTO FU","cityEn":"KYOTO SHI MINAMI KU","townEn":"HIGASHIKUJO KITAKARASUMACHO"},"6018021":{"prefectureJa":"京都府","cityJa":"京都市南区","townJa":"東九条宇賀辺町","prefectureEn":"KYOTO FU","cityEn":"KYOTO SHI MINAMI KU","townEn":"HIGASHIKUJO UKABECHO"},"6018022":{"prefectureJa":"京都府","cityJa":"京都市南区","townJa":"東九条北松ノ木町","prefectureEn":"KYOTO FU","cityEn":"KYOTO SHI MINAMI KU","townEn":"HIGASHIKUJO KITAMATSUNOKICHO"},"6018023":{"prefectureJa":"京都府","cityJa":"京都市南区","townJa":"東九条南松ノ木町","prefectureEn":"KYOTO FU","cityEn":"KYOTO SHI MINAMI KU","townEn":"HIGASHIKUJO MINAMIMATSUNOKICHO"},"6018024":{"prefectureJa":"京都府","cityJa":"京都市南区","townJa":"東九条東札辻町","prefectureEn":"KYOTO FU","cityEn":"KYOTO SHI MINAMI KU","townEn":"HIGASHIKUJO HIGASHIFUDANOTSUJICHO"},"6018025":{"prefectureJa":"京都府","cityJa":"京都市南区","townJa":"東九条柳下町","prefectureEn":"KYOTO FU","cityEn":"KYOTO SHI MINAMI KU","townEn":"HIGASHIKUJO YANAGINOSHITACHO"},"6018026":{"prefectureJa":"京都府","cityJa":"京都市南区","townJa":"東九条中札辻町","prefectureEn":"KYOTO FU","cityEn":"KYOTO SHI MINAMI KU","townEn":"HIGASHIKUJO NAKAFUDANOTSUJICHO"},"6018027":{"prefectureJa":"京都府","cityJa":"京都市南区","townJa":"東九条中御霊町","prefectureEn":"KYOTO FU","cityEn":"KYOTO SHI MINAMI KU","townEn":"HIGASHIKUJO NAKAGORYOCHO"},"6018028":{"prefectureJa":"京都府","cityJa":"京都市南区","townJa":"東九条東御霊町","prefectureEn":"KYOTO FU","cityEn":"KYOTO SHI MINAMI KU","townEn":"HIGASHIKUJO HIGASHIGORYOCHO"},"6018029":{"prefectureJa":"京都府","cityJa":"京都市南区","townJa":"東九条東松ノ木町","prefectureEn":"KYOTO FU","cityEn":"KYOTO SHI MINAMI KU","townEn":"HIGASHIKUJO HIGASHIMATSUNOKICHO"},"6018031":{"prefectureJa":"京都府","cityJa":"京都市南区","townJa":"東九条河辺町","prefectureEn":"KYOTO FU","cityEn":"KYOTO SHI MINAMI KU","townEn":"HIGASHIKUJO KAWABECHO"},"6018032":{"prefectureJa":"京都府","cityJa":"京都市南区","townJa":"東九条石田町","prefectureEn":"KYOTO FU","cityEn":"KYOTO SHI MINAMI KU","townEn":"HIGASHIKUJO ISHIDACHO"},"6018033":{"prefectureJa":"京都府","cityJa":"京都市南区","townJa":"東九条南石田町","prefectureEn":"KYOTO FU","cityEn":"KYOTO SHI MINAMI KU","townEn":"HIGASHIKUJO MINAMIISHIDACHO"},"6018034":{"prefectureJa":"京都府","cityJa":"京都市南区","townJa":"東九条南河辺町","prefectureEn":"KYOTO FU","cityEn":"KYOTO SHI MINAMI KU","townEn":"HIGASHIKUJO MINAMIKAWABECHO"},"6018035":{"prefectureJa":"京都府","cityJa":"京都市南区","townJa":"東九条南松田町","prefectureEn":"KYOTO FU","cityEn":"KYOTO SHI MINAMI KU","townEn":"HIGASHIKUJO MINAMIMATSUDACHO"},"6018036":{"prefectureJa":"京都府","cityJa":"京都市南区","townJa":"東九条松田町","prefectureEn":"KYOTO FU","cityEn":"KYOTO SHI MINAMI KU","townEn":"HIGASHIKUJO MATSUDACHO"},"6018037":{"prefectureJa":"京都府","cityJa":"京都市南区","townJa":"東九条西河辺町","prefectureEn":"KYOTO FU","cityEn":"KYOTO SHI MINAMI KU","townEn":"HIGASHIKUJO NISHIKAWABECHO"},"6018041":{"prefectureJa":"京都府","cityJa":"京都市南区","townJa":"東九条南烏丸町","prefectureEn":"KYOTO FU","cityEn":"KYOTO SHI MINAMI KU","townEn":"HIGASHIKUJO MINAMIKARASUMACHO"},"6018042":{"prefectureJa":"京都府","cityJa":"京都市南区","townJa":"東九条西御霊町","prefectureEn":"KYOTO FU","cityEn":"KYOTO SHI MINAMI KU","townEn":"HIGASHIKUJO NISHIGORYOCHO"},"6018043":{"prefectureJa":"京都府","cityJa":"京都市南区","townJa":"東九条西札辻町","prefectureEn":"KYOTO FU","cityEn":"KYOTO SHI MINAMI KU","townEn":"HIGASHIKUJO NISHIFUDANOTSUJICHO"},"6018044":{"prefectureJa":"京都府","cityJa":"京都市南区","townJa":"東九条明田町","prefectureEn":"KYOTO FU","cityEn":"KYOTO SHI MINAMI KU","townEn":"HIGASHIKUJO AKETACHO"},"6018045":{"prefectureJa":"京都府","cityJa":"京都市南区","townJa":"東九条西明田町","prefectureEn":"KYOTO FU","cityEn":"KYOTO SHI MINAMI KU","townEn":"HIGASHIKUJO NISHIAKETACHO"},"6018046":{"prefectureJa":"京都府","cityJa":"京都市南区","townJa":"東九条西山町","prefectureEn":"KYOTO FU","cityEn":"KYOTO SHI MINAMI KU","townEn":"HIGASHIKUJO NISHIYAMACHO"},"6018047":{"prefectureJa":"京都府","cityJa":"京都市南区","townJa":"東九条下殿田町","prefectureEn":"KYOTO FU","cityEn":"KYOTO SHI MINAMI KU","townEn":"HIGASHIKUJO SHIMOTONODACHO"},"6018048":{"prefectureJa":"京都府","cityJa":"京都市南区","townJa":"東九条中殿田町","prefectureEn":"KYOTO FU","cityEn":"KYOTO SHI MINAMI KU","townEn":"HIGASHIKUJO NAKATONODACHO"},"6018101":{"prefectureJa":"京都府","cityJa":"京都市南区","townJa":"上鳥羽高畠町","prefectureEn":"KYOTO FU","cityEn":"KYOTO SHI MINAMI KU","townEn":"KAMITOBA TAKAHATACHO"},"6018102":{"prefectureJa":"京都府","cityJa":"京都市南区","townJa":"上鳥羽菅田町","prefectureEn":"KYOTO FU","cityEn":"KYOTO SHI MINAMI KU","townEn":"KAMITOBA SUGATACHO"},"6018103":{"prefectureJa":"京都府","cityJa":"京都市南区","townJa":"上鳥羽仏現寺町","prefectureEn":"KYOTO FU","cityEn":"KYOTO SHI MINAMI KU","townEn":"KAMITOBA BUTSUGENJICHO"},"6018104":{"prefectureJa":"京都府","cityJa":"京都市南区","townJa":"上鳥羽角田町","prefectureEn":"KYOTO FU","cityEn":"KYOTO SHI MINAMI KU","townEn":"KAMITOBA TSUNODACHO"},"6018105":{"prefectureJa":"京都府","cityJa":"京都市南区","townJa":"上鳥羽上調子町","prefectureEn":"KYOTO FU","cityEn":"KYOTO SHI MINAMI KU","townEn":"KAMITOBA KAMICHOSHICHO"},"6018106":{"prefectureJa":"京都府","cityJa":"京都市南区","townJa":"上鳥羽北中ノ坪町","prefectureEn":"KYOTO FU","cityEn":"KYOTO SHI MINAMI KU","townEn":"KAMITOBA KITANAKANOTSUBOCHO"},"6018107":{"prefectureJa":"京都府","cityJa":"京都市南区","townJa":"上鳥羽南唐戸町","prefectureEn":"KYOTO FU","cityEn":"KYOTO SHI MINAMI KU","townEn":"KAMITOBA MINAMIKARATOCHO"},"6018108":{"prefectureJa":"京都府","cityJa":"京都市南区","townJa":"上鳥羽唐戸町","prefectureEn":"KYOTO FU","cityEn":"KYOTO SHI MINAMI KU","townEn":"KAMITOBA KARATOCHO"},"6018111":{"prefectureJa":"京都府","cityJa":"京都市南区","townJa":"上鳥羽苗代町","prefectureEn":"KYOTO FU","cityEn":"KYOTO SHI MINAMI KU","townEn":"KAMITOBA NAWASHIROCHO"},"6018112":{"prefectureJa":"京都府","cityJa":"京都市南区","townJa":"上鳥羽勧進橋町","prefectureEn":"KYOTO FU","cityEn":"KYOTO SHI MINAMI KU","townEn":"KAMITOBA KANJIMBASHICHO"},"6018113":{"prefectureJa":"京都府","cityJa":"京都市南区","townJa":"上鳥羽南苗代町","prefectureEn":"KYOTO FU","cityEn":"KYOTO SHI MINAMI KU","townEn":"KAMITOBA MINAMINAWASHIROCHO"},"6018114":{"prefectureJa":"京都府","cityJa":"京都市南区","townJa":"上鳥羽南鉾立町","prefectureEn":"KYOTO FU","cityEn":"KYOTO SHI MINAMI KU","townEn":"KAMITOBA MINAMIHOKOTATECHO"},"6018115":{"prefectureJa":"京都府","cityJa":"京都市南区","townJa":"上鳥羽尻切町","prefectureEn":"KYOTO FU","cityEn":"KYOTO SHI MINAMI KU","townEn":"KAMITOBA SHIRIKIRICHO"},"6018116":{"prefectureJa":"京都府","cityJa":"京都市南区","townJa":"上鳥羽鉾立町","prefectureEn":"KYOTO FU","cityEn":"KYOTO SHI MINAMI KU","townEn":"KAMITOBA HOKOTATECHO"},"6018121":{"prefectureJa":"京都府","cityJa":"京都市南区","townJa":"上鳥羽大物町","prefectureEn":"KYOTO FU","cityEn":"KYOTO SHI MINAMI KU","townEn":"KAMITOBA DAIMOTSUCHO"},"6018122":{"prefectureJa":"京都府","cityJa":"京都市南区","townJa":"上鳥羽北塔ノ本町","prefectureEn":"KYOTO FU","cityEn":"KYOTO SHI MINAMI KU","townEn":"KAMITOBA KITATONOMOTOCHO"},"6018123":{"prefectureJa":"京都府","cityJa":"京都市南区","townJa":"上鳥羽南塔ノ本町","prefectureEn":"KYOTO FU","cityEn":"KYOTO SHI MINAMI KU","townEn":"KAMITOBA MINAMITONOMOTOCHO"},"6018126":{"prefectureJa":"京都府","cityJa":"京都市南区","townJa":"上鳥羽南花名町","prefectureEn":"KYOTO FU","cityEn":"KYOTO SHI MINAMI KU","townEn":"KAMITOBA MINAMIHANANACHO"},"6018127":{"prefectureJa":"京都府","cityJa":"京都市南区","townJa":"上鳥羽北花名町","prefectureEn":"KYOTO FU","cityEn":"KYOTO SHI MINAMI KU","townEn":"KAMITOBA KITAHANANACHO"},"6018128":{"prefectureJa":"京都府","cityJa":"京都市南区","townJa":"上鳥羽大柳町","prefectureEn":"KYOTO FU","cityEn":"KYOTO SHI MINAMI KU","townEn":"KAMITOBA OYANAGICHO"},"6018131":{"prefectureJa":"京都府","cityJa":"京都市南区","townJa":"上鳥羽鴨田町","prefectureEn":"KYOTO FU","cityEn":"KYOTO SHI MINAMI KU","townEn":"KAMITOBA KAMONDENCHO"},"6018132":{"prefectureJa":"京都府","cityJa":"京都市南区","townJa":"上鳥羽町田町","prefectureEn":"KYOTO FU","cityEn":"KYOTO SHI MINAMI KU","townEn":"KAMITOBA CHODAMACHI"},"6018133":{"prefectureJa":"京都府","cityJa":"京都市南区","townJa":"上鳥羽藁田町","prefectureEn":"KYOTO FU","cityEn":"KYOTO SHI MINAMI KU","townEn":"KAMITOBA WARANDENCHO"},"6018134":{"prefectureJa":"京都府","cityJa":"京都市南区","townJa":"上鳥羽大溝町","prefectureEn":"KYOTO FU","cityEn":"KYOTO SHI MINAMI KU","townEn":"KAMITOBA OMIZOCHO"},"6018135":{"prefectureJa":"京都府","cityJa":"京都市南区","townJa":"上鳥羽石橋町","prefectureEn":"KYOTO FU","cityEn":"KYOTO SHI MINAMI KU","townEn":"KAMITOBA ISHIBASHICHO"},"6018136":{"prefectureJa":"京都府","cityJa":"京都市南区","townJa":"上鳥羽岩ノ本町","prefectureEn":"KYOTO FU","cityEn":"KYOTO SHI MINAMI KU","townEn":"KAMITOBA IWANOMOTOCHO"},"6018137":{"prefectureJa":"京都府","cityJa":"京都市南区","townJa":"上鳥羽城ケ前町","prefectureEn":"KYOTO FU","cityEn":"KYOTO SHI MINAMI KU","townEn":"KAMITOBA SHIROGAMAECHO"},"6018138":{"prefectureJa":"京都府","cityJa":"京都市南区","townJa":"上鳥羽北岩ノ本町","prefectureEn":"KYOTO FU","cityEn":"KYOTO SHI MINAMI KU","townEn":"KAMITOBA KITAIWANOMOTOCHO"},"6018139":{"prefectureJa":"京都府","cityJa":"京都市南区","townJa":"上鳥羽南岩ノ本町","prefectureEn":"KYOTO FU","cityEn":"KYOTO SHI MINAMI KU","townEn":"KAMITOBA MINAMIIWANOMOTOCHO"},"6018141":{"prefectureJa":"京都府","cityJa":"京都市南区","townJa":"上鳥羽卯ノ花町","prefectureEn":"KYOTO FU","cityEn":"KYOTO SHI MINAMI KU","townEn":"KAMITOBA UNOHANACHO"},"6018142":{"prefectureJa":"京都府","cityJa":"京都市南区","townJa":"上鳥羽中河原町","prefectureEn":"KYOTO FU","cityEn":"KYOTO SHI MINAMI KU","townEn":"KAMITOBA NAKAGAWARACHO"},"6018143":{"prefectureJa":"京都府","cityJa":"京都市南区","townJa":"上鳥羽麻ノ本町","prefectureEn":"KYOTO FU","cityEn":"KYOTO SHI MINAMI KU","townEn":"KAMITOBA ASANOMOTOCHO"},"6018144":{"prefectureJa":"京都府","cityJa":"京都市南区","townJa":"上鳥羽火打形町","prefectureEn":"KYOTO FU","cityEn":"KYOTO SHI MINAMI KU","townEn":"KAMITOBA HIUCHIGATACHO"},"6018145":{"prefectureJa":"京都府","cityJa":"京都市南区","townJa":"上鳥羽西浦町","prefectureEn":"KYOTO FU","cityEn":"KYOTO SHI MINAMI KU","townEn":"KAMITOBA NISHIURACHO"},"6018146":{"prefectureJa":"京都府","cityJa":"京都市南区","townJa":"上鳥羽奈須野町","prefectureEn":"KYOTO FU","cityEn":"KYOTO SHI MINAMI KU","townEn":"KAMITOBA NASUNOCHO"},"6018151":{"prefectureJa":"京都府","cityJa":"京都市南区","townJa":"上鳥羽塔ノ森東向町","prefectureEn":"KYOTO FU","cityEn":"KYOTO SHI MINAMI KU","townEn":"KAMITOBATONOMORI HIGASHIMUKOCHO"},"6018152":{"prefectureJa":"京都府","cityJa":"京都市南区","townJa":"上鳥羽塔ノ森洲崎町","prefectureEn":"KYOTO FU","cityEn":"KYOTO SHI MINAMI KU","townEn":"KAMITOBATONOMORI SUZAKICHO"},"6018153":{"prefectureJa":"京都府","cityJa":"京都市南区","townJa":"上鳥羽塔ノ森下河原","prefectureEn":"KYOTO FU","cityEn":"KYOTO SHI MINAMI KU","townEn":"KAMITOBATONOMORI SHIMOKAWARA"},"6018154":{"prefectureJa":"京都府","cityJa":"京都市南区","townJa":"上鳥羽塔ノ森柳原","prefectureEn":"KYOTO FU","cityEn":"KYOTO SHI MINAMI KU","townEn":"KAMITOBATONOMORI YANAGIHARA"},"6018155":{"prefectureJa":"京都府","cityJa":"京都市南区","townJa":"上鳥羽塔ノ森上河原","prefectureEn":"KYOTO FU","cityEn":"KYOTO SHI MINAMI KU","townEn":"KAMITOBATONOMORI KAMIKAWARA"},"6018161":{"prefectureJa":"京都府","cityJa":"京都市南区","townJa":"上鳥羽塔ノ森梅ノ木","prefectureEn":"KYOTO FU","cityEn":"KYOTO SHI MINAMI KU","townEn":"KAMITOBATONOMORI UMENOKI"},"6018162":{"prefectureJa":"京都府","cityJa":"京都市南区","townJa":"上鳥羽塔ノ森柴東町","prefectureEn":"KYOTO FU","cityEn":"KYOTO SHI MINAMI KU","townEn":"KAMITOBATONOMORI SHIBAHIGASHICHO"},"6018163":{"prefectureJa":"京都府","cityJa":"京都市南区","townJa":"上鳥羽塔ノ森江川町","prefectureEn":"KYOTO FU","cityEn":"KYOTO SHI MINAMI KU","townEn":"KAMITOBATONOMORI EGAWACHO"},"6018164":{"prefectureJa":"京都府","cityJa":"京都市南区","townJa":"上鳥羽塔ノ森四ツ谷町","prefectureEn":"KYOTO FU","cityEn":"KYOTO SHI MINAMI KU","townEn":"KAMITOBATONOMORI YOTSUYACHO"},"6018165":{"prefectureJa":"京都府","cityJa":"京都市南区","townJa":"上鳥羽塔ノ森西河原町","prefectureEn":"KYOTO FU","cityEn":"KYOTO SHI MINAMI KU","townEn":"KAMITOBATONOMORI NISHIGAWARACHO"},"6018166":{"prefectureJa":"京都府","cityJa":"京都市南区","townJa":"上鳥羽塔ノ森下開ノ内","prefectureEn":"KYOTO FU","cityEn":"KYOTO SHI MINAMI KU","townEn":"KAMITOBATONOMORI SHIMOHIRAKINOCHI"},"6018167":{"prefectureJa":"京都府","cityJa":"京都市南区","townJa":"上鳥羽塔ノ森上開ノ内","prefectureEn":"KYOTO FU","cityEn":"KYOTO SHI MINAMI KU","townEn":"KAMITOBATONOMORI KAMIHIRAKINOCHI"},"6018171":{"prefectureJa":"京都府","cityJa":"京都市南区","townJa":"上鳥羽川端町","prefectureEn":"KYOTO FU","cityEn":"KYOTO SHI MINAMI KU","townEn":"KAMITOBA KAWABATACHO"},"6018172":{"prefectureJa":"京都府","cityJa":"京都市南区","townJa":"上鳥羽鍋ケ渕町","prefectureEn":"KYOTO FU","cityEn":"KYOTO SHI MINAMI KU","townEn":"KAMITOBA NABEGAFUCHICHO"},"6018173":{"prefectureJa":"京都府","cityJa":"京都市南区","townJa":"上鳥羽八王神町","prefectureEn":"KYOTO FU","cityEn":"KYOTO SHI MINAMI KU","townEn":"KAMITOBA HACHIOJINCHO"},"6018174":{"prefectureJa":"京都府","cityJa":"京都市南区","townJa":"上鳥羽清井町","prefectureEn":"KYOTO FU","cityEn":"KYOTO SHI MINAMI KU","townEn":"KAMITOBA KIYOICHO"},"6018175":{"prefectureJa":"京都府","cityJa":"京都市南区","townJa":"上鳥羽金仏町","prefectureEn":"KYOTO FU","cityEn":"KYOTO SHI MINAMI KU","townEn":"KAMITOBA KANABOTOKECHO"},"6018176":{"prefectureJa":"京都府","cityJa":"京都市南区","townJa":"上鳥羽山ノ本町","prefectureEn":"KYOTO FU","cityEn":"KYOTO SHI MINAMI KU","townEn":"KAMITOBA YAMANOMOTOCHO"},"6018177":{"prefectureJa":"京都府","cityJa":"京都市南区","townJa":"上鳥羽馬廻町","prefectureEn":"KYOTO FU","cityEn":"KYOTO SHI MINAMI KU","townEn":"KAMITOBA UMAMAWASHICHO"},"6018178":{"prefectureJa":"京都府","cityJa":"京都市南区","townJa":"上鳥羽南戒光町","prefectureEn":"KYOTO FU","cityEn":"KYOTO SHI MINAMI KU","townEn":"KAMITOBA MINAMIKAIKOCHO"},"6018181":{"prefectureJa":"京都府","cityJa":"京都市南区","townJa":"上鳥羽堀子町","prefectureEn":"KYOTO FU","cityEn":"KYOTO SHI MINAMI KU","townEn":"KAMITOBA HORIKOCHO"},"6018182":{"prefectureJa":"京都府","cityJa":"京都市南区","townJa":"上鳥羽北島田町","prefectureEn":"KYOTO FU","cityEn":"KYOTO SHI MINAMI KU","townEn":"KAMITOBA KITASHIMADACHO"},"6018183":{"prefectureJa":"京都府","cityJa":"京都市南区","townJa":"上鳥羽南島田町","prefectureEn":"KYOTO FU","cityEn":"KYOTO SHI MINAMI KU","townEn":"KAMITOBA MINAMISHIMADACHO"},"6018184":{"prefectureJa":"京都府","cityJa":"京都市南区","townJa":"上鳥羽南村山町","prefectureEn":"KYOTO FU","cityEn":"KYOTO SHI MINAMI KU","townEn":"KAMITOBA MINAMIMURAYAMACHO"},"6018185":{"prefectureJa":"京都府","cityJa":"京都市南区","townJa":"上鳥羽戒光町","prefectureEn":"KYOTO FU","cityEn":"KYOTO SHI MINAMI KU","townEn":"KAMITOBA KAIKOCHO"},"6018186":{"prefectureJa":"京都府","cityJa":"京都市南区","townJa":"上鳥羽北戒光町","prefectureEn":"KYOTO FU","cityEn":"KYOTO SHI MINAMI KU","townEn":"KAMITOBA KITAKAIKOCHO"},"6018187":{"prefectureJa":"京都府","cityJa":"京都市南区","townJa":"上鳥羽北村山町","prefectureEn":"KYOTO FU","cityEn":"KYOTO SHI MINAMI KU","townEn":"KAMITOBA KITAMURAYAMACHO"},"6018188":{"prefectureJa":"京都府","cityJa":"京都市南区","townJa":"上鳥羽南中ノ坪町","prefectureEn":"KYOTO FU","cityEn":"KYOTO SHI MINAMI KU","townEn":"KAMITOBA MINAMINAKANOTSUBOCHO"},"6018201":{"prefectureJa":"京都府","cityJa":"京都市南区","townJa":"久世川原町","prefectureEn":"KYOTO FU","cityEn":"KYOTO SHI MINAMI KU","townEn":"KUZE KAWAHARACHO"},"6018202":{"prefectureJa":"京都府","cityJa":"京都市南区","townJa":"久世大築町","prefectureEn":"KYOTO FU","cityEn":"KYOTO SHI MINAMI KU","townEn":"KUZE OTSUKICHO"},"6018203":{"prefectureJa":"京都府","cityJa":"京都市南区","townJa":"久世築山町","prefectureEn":"KYOTO FU","cityEn":"KYOTO SHI MINAMI KU","townEn":"KUZE TSUKIYAMACHO"},"6018204":{"prefectureJa":"京都府","cityJa":"京都市南区","townJa":"久世東土川町","prefectureEn":"KYOTO FU","cityEn":"KYOTO SHI MINAMI KU","townEn":"KUZE HIGASHITSUCHIKAWACHO"},"6018205":{"prefectureJa":"京都府","cityJa":"京都市南区","townJa":"久世殿城町","prefectureEn":"KYOTO FU","cityEn":"KYOTO SHI MINAMI KU","townEn":"KUZE TONOSHIROCHO"},"6018206":{"prefectureJa":"京都府","cityJa":"京都市南区","townJa":"久世大薮町","prefectureEn":"KYOTO FU","cityEn":"KYOTO SHI MINAMI KU","townEn":"KUZE OYABUCHO"},"6018207":{"prefectureJa":"京都府","cityJa":"京都市南区","townJa":"久世中久町","prefectureEn":"KYOTO FU","cityEn":"KYOTO SHI MINAMI KU","townEn":"KUZE NAKAHISACHO"},"6018211":{"prefectureJa":"京都府","cityJa":"京都市南区","townJa":"久世高田町","prefectureEn":"KYOTO FU","cityEn":"KYOTO SHI MINAMI KU","townEn":"KUZE TAKADACHO"},"6018212":{"prefectureJa":"京都府","cityJa":"京都市南区","townJa":"久世上久世町","prefectureEn":"KYOTO FU","cityEn":"KYOTO SHI MINAMI KU","townEn":"KUZE KAMIKUZECHO"},"6018213":{"prefectureJa":"京都府","cityJa":"京都市南区","townJa":"久世中久世町","prefectureEn":"KYOTO FU","cityEn":"KYOTO SHI MINAMI KU","townEn":"KUZE NAKAKUZECHO"},"6018301":{"prefectureJa":"京都府","cityJa":"京都市南区","townJa":"吉祥院西ノ庄西浦町","prefectureEn":"KYOTO FU","cityEn":"KYOTO SHI MINAMI KU","townEn":"KISSHOINNISHINOSHO NISHIURACHO"},"6018302":{"prefectureJa":"京都府","cityJa":"京都市南区","townJa":"吉祥院西ノ庄淵ノ西町","prefectureEn":"KYOTO FU","cityEn":"KYOTO SHI MINAMI KU","townEn":"KISSHOINNISHINOSHO FUCHINONISHICHO"},"6018303":{"prefectureJa":"京都府","cityJa":"京都市南区","townJa":"吉祥院西ノ庄西中町","prefectureEn":"KYOTO FU","cityEn":"KYOTO SHI MINAMI KU","townEn":"KISSHOINNISHINOSHO NISHINAKACHO"},"6018304":{"prefectureJa":"京都府","cityJa":"京都市南区","townJa":"吉祥院前河原町","prefectureEn":"KYOTO FU","cityEn":"KYOTO SHI MINAMI KU","townEn":"KISSHOIN MAEGAWARACHO"},"6018305":{"prefectureJa":"京都府","cityJa":"京都市南区","townJa":"吉祥院宮ノ東町","prefectureEn":"KYOTO FU","cityEn":"KYOTO SHI MINAMI KU","townEn":"KISSHOIN MIYANOHIGASHICHO"},"6018306":{"prefectureJa":"京都府","cityJa":"京都市南区","townJa":"吉祥院宮ノ西町","prefectureEn":"KYOTO FU","cityEn":"KYOTO SHI MINAMI KU","townEn":"KISSHOIN MIYANONISHICHO"},"6018307":{"prefectureJa":"京都府","cityJa":"京都市南区","townJa":"吉祥院向田西町","prefectureEn":"KYOTO FU","cityEn":"KYOTO SHI MINAMI KU","townEn":"KISSHOIN MUKAIDANISHICHO"},"6018308":{"prefectureJa":"京都府","cityJa":"京都市南区","townJa":"吉祥院向田東町","prefectureEn":"KYOTO FU","cityEn":"KYOTO SHI MINAMI KU","townEn":"KISSHOIN MUKAIDAHIGASHICHO"},"6018309":{"prefectureJa":"京都府","cityJa":"京都市南区","townJa":"吉祥院西ノ庄向田町","prefectureEn":"KYOTO FU","cityEn":"KYOTO SHI MINAMI KU","townEn":"KISSHOINNISHINOSHO MUKAIDACHO"},"6018310":{"prefectureJa":"京都府","cityJa":"京都市南区","townJa":"吉祥院西ノ庄猪之馬場町","prefectureEn":"KYOTO FU","cityEn":"KYOTO SHI MINAMI KU","townEn":"KISSHOINNISHINOSHO INOBABACHO"},"6018311":{"prefectureJa":"京都府","cityJa":"京都市南区","townJa":"吉祥院西ノ庄東屋敷町","prefectureEn":"KYOTO FU","cityEn":"KYOTO SHI MINAMI KU","townEn":"KISSHOINNISHINOSHO HIGASHIYASHIKICH"},"6018312":{"prefectureJa":"京都府","cityJa":"京都市南区","townJa":"吉祥院西ノ庄門口町","prefectureEn":"KYOTO FU","cityEn":"KYOTO SHI MINAMI KU","townEn":"KISSHOINNISHINOSHO MONGUCHICHO"},"6018313":{"prefectureJa":"京都府","cityJa":"京都市南区","townJa":"吉祥院中島町","prefectureEn":"KYOTO FU","cityEn":"KYOTO SHI MINAMI KU","townEn":"KISSHOIN NAKAJIMACHO"},"6018314":{"prefectureJa":"京都府","cityJa":"京都市南区","townJa":"吉祥院井ノ口町","prefectureEn":"KYOTO FU","cityEn":"KYOTO SHI MINAMI KU","townEn":"KISSHOIN INOKUCHICHO"},"6018315":{"prefectureJa":"京都府","cityJa":"京都市南区","townJa":"吉祥院車道町","prefectureEn":"KYOTO FU","cityEn":"KYOTO SHI MINAMI KU","townEn":"KISSHOIN KURUMAMICHICHO"},"6018316":{"prefectureJa":"京都府","cityJa":"京都市南区","townJa":"吉祥院池ノ内町","prefectureEn":"KYOTO FU","cityEn":"KYOTO SHI MINAMI KU","townEn":"KISSHOIN IKENOCHICHO"},"6018317":{"prefectureJa":"京都府","cityJa":"京都市南区","townJa":"吉祥院新田弐ノ段町","prefectureEn":"KYOTO FU","cityEn":"KYOTO SHI MINAMI KU","townEn":"KISSHOINSHINDEN NINODANCHO"},"6018318":{"prefectureJa":"京都府","cityJa":"京都市南区","townJa":"吉祥院三ノ宮西町","prefectureEn":"KYOTO FU","cityEn":"KYOTO SHI MINAMI KU","townEn":"KISSHOIN SANNOMIYANISHIMACHI"},"6018319":{"prefectureJa":"京都府","cityJa":"京都市南区","townJa":"吉祥院三ノ宮町","prefectureEn":"KYOTO FU","cityEn":"KYOTO SHI MINAMI KU","townEn":"KISSHOIN SANNOMIYACHO"},"6018321":{"prefectureJa":"京都府","cityJa":"京都市南区","townJa":"吉祥院西定成町","prefectureEn":"KYOTO FU","cityEn":"KYOTO SHI MINAMI KU","townEn":"KISSHOIN NISHISADANARICHO"},"6018322":{"prefectureJa":"京都府","cityJa":"京都市南区","townJa":"吉祥院定成町","prefectureEn":"KYOTO FU","cityEn":"KYOTO SHI MINAMI KU","townEn":"KISSHOIN SADANARICHO"},"6018323":{"prefectureJa":"京都府","cityJa":"京都市南区","townJa":"吉祥院春日町","prefectureEn":"KYOTO FU","cityEn":"KYOTO SHI MINAMI KU","townEn":"KISSHOIN KASUGACHO"},"6018324":{"prefectureJa":"京都府","cityJa":"京都市南区","townJa":"吉祥院落合町","prefectureEn":"KYOTO FU","cityEn":"KYOTO SHI MINAMI KU","townEn":"KISSHOIN OCHIAICHO"},"6018325":{"prefectureJa":"京都府","cityJa":"京都市南区","townJa":"吉祥院八反田町","prefectureEn":"KYOTO FU","cityEn":"KYOTO SHI MINAMI KU","townEn":"KISSHOIN HATSUTANDACHO"},"6018326":{"prefectureJa":"京都府","cityJa":"京都市南区","townJa":"吉祥院南落合町","prefectureEn":"KYOTO FU","cityEn":"KYOTO SHI MINAMI KU","townEn":"KISSHOIN MINAMIOCHIAICHO"},"6018327":{"prefectureJa":"京都府","cityJa":"京都市南区","townJa":"吉祥院御池町","prefectureEn":"KYOTO FU","cityEn":"KYOTO SHI MINAMI KU","townEn":"KISSHOIN OIKECHO"},"6018328":{"prefectureJa":"京都府","cityJa":"京都市南区","townJa":"吉祥院九条町","prefectureEn":"KYOTO FU","cityEn":"KYOTO SHI MINAMI KU","townEn":"KISSHOIN KUJOCHO"},"6018329":{"prefectureJa":"京都府","cityJa":"京都市南区","townJa":"吉祥院清水町","prefectureEn":"KYOTO FU","cityEn":"KYOTO SHI MINAMI KU","townEn":"KISSHOIN SHIMIZUCHO"},"6018330":{"prefectureJa":"京都府","cityJa":"京都市南区","townJa":"吉祥院船戸町","prefectureEn":"KYOTO FU","cityEn":"KYOTO SHI MINAMI KU","townEn":"KISSHOIN FUNATOCHO"},"6018331":{"prefectureJa":"京都府","cityJa":"京都市南区","townJa":"吉祥院政所町","prefectureEn":"KYOTO FU","cityEn":"KYOTO SHI MINAMI KU","townEn":"KISSHOIN MANDOKOROCHO"},"6018332":{"prefectureJa":"京都府","cityJa":"京都市南区","townJa":"吉祥院高畑町","prefectureEn":"KYOTO FU","cityEn":"KYOTO SHI MINAMI KU","townEn":"KISSHOIN TAKAHATACHO"},"6018333":{"prefectureJa":"京都府","cityJa":"京都市南区","townJa":"吉祥院東浦町","prefectureEn":"KYOTO FU","cityEn":"KYOTO SHI MINAMI KU","townEn":"KISSHOIN HIGASHIURACHO"},"6018334":{"prefectureJa":"京都府","cityJa":"京都市南区","townJa":"吉祥院東砂ノ町","prefectureEn":"KYOTO FU","cityEn":"KYOTO SHI MINAMI KU","townEn":"KISSHOIN HIGASHISUNANOCHO"},"6018335":{"prefectureJa":"京都府","cityJa":"京都市南区","townJa":"吉祥院砂ノ町","prefectureEn":"KYOTO FU","cityEn":"KYOTO SHI MINAMI KU","townEn":"KISSHOIN SUNANOCHO"},"6018336":{"prefectureJa":"京都府","cityJa":"京都市南区","townJa":"吉祥院菅原町","prefectureEn":"KYOTO FU","cityEn":"KYOTO SHI MINAMI KU","townEn":"KISSHOIN SUGAHARACHO"},"6018337":{"prefectureJa":"京都府","cityJa":"京都市南区","townJa":"吉祥院這登東町","prefectureEn":"KYOTO FU","cityEn":"KYOTO SHI MINAMI KU","townEn":"KISSHOIN HAINOBORIHIGASHIMACHI"},"6018338":{"prefectureJa":"京都府","cityJa":"京都市南区","townJa":"吉祥院西ノ内町","prefectureEn":"KYOTO FU","cityEn":"KYOTO SHI MINAMI KU","townEn":"KISSHOIN NISHINOCHICHO"},"6018339":{"prefectureJa":"京都府","cityJa":"京都市南区","townJa":"吉祥院里ノ内町","prefectureEn":"KYOTO FU","cityEn":"KYOTO SHI MINAMI KU","townEn":"KISSHOIN SATONOCHICHO"},"6018341":{"prefectureJa":"京都府","cityJa":"京都市南区","townJa":"吉祥院前田町","prefectureEn":"KYOTO FU","cityEn":"KYOTO SHI MINAMI KU","townEn":"KISSHOIN MAEDACHO"},"6018342":{"prefectureJa":"京都府","cityJa":"京都市南区","townJa":"吉祥院東前田町","prefectureEn":"KYOTO FU","cityEn":"KYOTO SHI MINAMI KU","townEn":"KISSHOIN HIGASHIMAEDACHO"},"6018343":{"prefectureJa":"京都府","cityJa":"京都市南区","townJa":"吉祥院稲葉町","prefectureEn":"KYOTO FU","cityEn":"KYOTO SHI MINAMI KU","townEn":"KISSHOIN INABACHO"},"6018344":{"prefectureJa":"京都府","cityJa":"京都市南区","townJa":"吉祥院蒔絵町","prefectureEn":"KYOTO FU","cityEn":"KYOTO SHI MINAMI KU","townEn":"KISSHOIN MAKIECHO"},"6018345":{"prefectureJa":"京都府","cityJa":"京都市南区","townJa":"吉祥院蒔絵南町","prefectureEn":"KYOTO FU","cityEn":"KYOTO SHI MINAMI KU","townEn":"KISSHOIN MAKIEMINAMICHO"},"6018346":{"prefectureJa":"京都府","cityJa":"京都市南区","townJa":"吉祥院池田南町","prefectureEn":"KYOTO FU","cityEn":"KYOTO SHI MINAMI KU","townEn":"KISSHOIN IKEDAMINAMICHO"},"6018347":{"prefectureJa":"京都府","cityJa":"京都市南区","townJa":"吉祥院観音堂南町","prefectureEn":"KYOTO FU","cityEn":"KYOTO SHI MINAMI KU","townEn":"KISSHOIN KANNONDOMINAMICHO"},"6018348":{"prefectureJa":"京都府","cityJa":"京都市南区","townJa":"吉祥院観音堂町","prefectureEn":"KYOTO FU","cityEn":"KYOTO SHI MINAMI KU","townEn":"KISSHOIN KANNONDOCHO"},"6018349":{"prefectureJa":"京都府","cityJa":"京都市南区","townJa":"吉祥院池田町","prefectureEn":"KYOTO FU","cityEn":"KYOTO SHI MINAMI KU","townEn":"KISSHOIN IKEDACHO"},"6018351":{"prefectureJa":"京都府","cityJa":"京都市南区","townJa":"吉祥院這登西町","prefectureEn":"KYOTO FU","cityEn":"KYOTO SHI MINAMI KU","townEn":"KISSHOIN HAINOBORINISHIMACHI"},"6018352":{"prefectureJa":"京都府","cityJa":"京都市南区","townJa":"吉祥院西浦町","prefectureEn":"KYOTO FU","cityEn":"KYOTO SHI MINAMI KU","townEn":"KISSHOIN NISHIURACHO"},"6018353":{"prefectureJa":"京都府","cityJa":"京都市南区","townJa":"吉祥院這登中町","prefectureEn":"KYOTO FU","cityEn":"KYOTO SHI MINAMI KU","townEn":"KISSHOIN HAINOBORINAKAMACHI"},"6018354":{"prefectureJa":"京都府","cityJa":"京都市南区","townJa":"吉祥院仁木ノ森町","prefectureEn":"KYOTO FU","cityEn":"KYOTO SHI MINAMI KU","townEn":"KISSHOIN NIKINOMORICHO"},"6018355":{"prefectureJa":"京都府","cityJa":"京都市南区","townJa":"吉祥院石原堂ノ後町","prefectureEn":"KYOTO FU","cityEn":"KYOTO SHI MINAMI KU","townEn":"KISSHOINISHIHARA DONOSHIROCHO"},"6018356":{"prefectureJa":"京都府","cityJa":"京都市南区","townJa":"吉祥院石原京道町","prefectureEn":"KYOTO FU","cityEn":"KYOTO SHI MINAMI KU","townEn":"KISSHOINISHIHARA KYOMICHICHO"},"6018357":{"prefectureJa":"京都府","cityJa":"京都市南区","townJa":"吉祥院石原堂ノ後西町","prefectureEn":"KYOTO FU","cityEn":"KYOTO SHI MINAMI KU","townEn":"KISSHOINISHIHARA DONOSHIRONISHIMACH"},"6018361":{"prefectureJa":"京都府","cityJa":"京都市南区","townJa":"吉祥院石原東之口町","prefectureEn":"KYOTO FU","cityEn":"KYOTO SHI MINAMI KU","townEn":"KISSHOINISHIHARA HIGASHINOKUCHICHO"},"6018362":{"prefectureJa":"京都府","cityJa":"京都市南区","townJa":"吉祥院長田町","prefectureEn":"KYOTO FU","cityEn":"KYOTO SHI MINAMI KU","townEn":"KISSHOIN NAGATACHO"},"6018363":{"prefectureJa":"京都府","cityJa":"京都市南区","townJa":"吉祥院嶋野間詰町","prefectureEn":"KYOTO FU","cityEn":"KYOTO SHI MINAMI KU","townEn":"KISSHOINSHIMA NOMAZUMECHO"},"6018364":{"prefectureJa":"京都府","cityJa":"京都市南区","townJa":"吉祥院石原南町","prefectureEn":"KYOTO FU","cityEn":"KYOTO SHI MINAMI KU","townEn":"KISSHOINISHIHARA MINAMICHO"},"6018365":{"prefectureJa":"京都府","cityJa":"京都市南区","townJa":"吉祥院石原開町","prefectureEn":"KYOTO FU","cityEn":"KYOTO SHI MINAMI KU","townEn":"KISSHOINISHIHARA HIRAKIMACHI"},"6018366":{"prefectureJa":"京都府","cityJa":"京都市南区","townJa":"吉祥院石原西町","prefectureEn":"KYOTO FU","cityEn":"KYOTO SHI MINAMI KU","townEn":"KISSHOINISHIHARA NISHIMACHI"},"6018367":{"prefectureJa":"京都府","cityJa":"京都市南区","townJa":"吉祥院石原町","prefectureEn":"KYOTO FU","cityEn":"KYOTO SHI MINAMI KU","townEn":"KISSHOIN ISHIHARACHO"},"6018371":{"prefectureJa":"京都府","cityJa":"京都市南区","townJa":"吉祥院嶋樫山町","prefectureEn":"KYOTO FU","cityEn":"KYOTO SHI MINAMI KU","townEn":"KISSHOINSHIMA KATAGIYAMACHO"},"6018372":{"prefectureJa":"京都府","cityJa":"京都市南区","townJa":"吉祥院嶋高町","prefectureEn":"KYOTO FU","cityEn":"KYOTO SHI MINAMI KU","townEn":"KISSHOINSHIMA TAKAMACHI"},"6018373":{"prefectureJa":"京都府","cityJa":"京都市南区","townJa":"吉祥院嶋出在家町","prefectureEn":"KYOTO FU","cityEn":"KYOTO SHI MINAMI KU","townEn":"KISSHOINSHIMA DEZAIKECHO"},"6018374":{"prefectureJa":"京都府","cityJa":"京都市南区","townJa":"吉祥院嶋笠井町","prefectureEn":"KYOTO FU","cityEn":"KYOTO SHI MINAMI KU","townEn":"KISSHOINSHIMA KASAICHO"},"6018375":{"prefectureJa":"京都府","cityJa":"京都市南区","townJa":"吉祥院嶋西浦","prefectureEn":"KYOTO FU","cityEn":"KYOTO SHI MINAMI KU","townEn":"KISSHOINSHIMA NISHIURA"},"6018376":{"prefectureJa":"京都府","cityJa":"京都市南区","townJa":"吉祥院嶋中ノ島","prefectureEn":"KYOTO FU","cityEn":"KYOTO SHI MINAMI KU","townEn":"KISSHOINSHIMA NAKANOSHIMA"},"6018377":{"prefectureJa":"京都府","cityJa":"京都市南区","townJa":"吉祥院嶋堂ノ裏","prefectureEn":"KYOTO FU","cityEn":"KYOTO SHI MINAMI KU","townEn":"KISSHOINSHIMA DONORA"},"6018378":{"prefectureJa":"京都府","cityJa":"京都市南区","townJa":"吉祥院嶋堤外","prefectureEn":"KYOTO FU","cityEn":"KYOTO SHI MINAMI KU","townEn":"KISSHOINSHIMA TSUTSUMISOTO"},"6018379":{"prefectureJa":"京都府","cityJa":"京都市南区","townJa":"吉祥院嶋川原田町","prefectureEn":"KYOTO FU","cityEn":"KYOTO SHI MINAMI KU","townEn":"KISSHOINSHIMA KAWARADACHO"},"6018380":{"prefectureJa":"京都府","cityJa":"京都市南区","townJa":"吉祥院新田下ノ向町","prefectureEn":"KYOTO FU","cityEn":"KYOTO SHI MINAMI KU","townEn":"KISSHOINSHINDEN SHIMONOMUKAICHO"},"6018381":{"prefectureJa":"京都府","cityJa":"京都市南区","townJa":"吉祥院西ノ茶屋町","prefectureEn":"KYOTO FU","cityEn":"KYOTO SHI MINAMI KU","townEn":"KISSHOIN NISHINOCHAYACHO"},"6018382":{"prefectureJa":"京都府","cityJa":"京都市南区","townJa":"吉祥院石原上川原町","prefectureEn":"KYOTO FU","cityEn":"KYOTO SHI MINAMI KU","townEn":"KISSHOINISHIHARA KAMIKAWARACHO"},"6018383":{"prefectureJa":"京都府","cityJa":"京都市南区","townJa":"吉祥院石原長田町","prefectureEn":"KYOTO FU","cityEn":"KYOTO SHI MINAMI KU","townEn":"KISSHOINISHIHARA NAGATACHO"},"6018384":{"prefectureJa":"京都府","cityJa":"京都市南区","townJa":"吉祥院石原野上町","prefectureEn":"KYOTO FU","cityEn":"KYOTO SHI MINAMI KU","townEn":"KISSHOINISHIHARA NOGAMICHO"},"6018385":{"prefectureJa":"京都府","cityJa":"京都市南区","townJa":"吉祥院石原葭縁","prefectureEn":"KYOTO FU","cityEn":"KYOTO SHI MINAMI KU","townEn":"KISSHOINISHIHARA YOSHIBERI"},"6018386":{"prefectureJa":"京都府","cityJa":"京都市南区","townJa":"吉祥院石原割畑","prefectureEn":"KYOTO FU","cityEn":"KYOTO SHI MINAMI KU","townEn":"KISSHOINISHIHARA WARIHATA"},"6018387":{"prefectureJa":"京都府","cityJa":"京都市南区","townJa":"吉祥院石原橋裏","prefectureEn":"KYOTO FU","cityEn":"KYOTO SHI MINAMI KU","townEn":"KISSHOINISHIHARA HASHIURA"},"6018388":{"prefectureJa":"京都府","cityJa":"京都市南区","townJa":"吉祥院石原西ノ開町","prefectureEn":"KYOTO FU","cityEn":"KYOTO SHI MINAMI KU","townEn":"KISSHOINISHIHARA NISHINOHIRAKICHO"},"6018389":{"prefectureJa":"京都府","cityJa":"京都市南区","townJa":"吉祥院石原橋上","prefectureEn":"KYOTO FU","cityEn":"KYOTO SHI MINAMI KU","townEn":"KISSHOINISHIHARA HASHIKAMI"},"6018390":{"prefectureJa":"京都府","cityJa":"京都市南区","townJa":"吉祥院流作町","prefectureEn":"KYOTO FU","cityEn":"KYOTO SHI MINAMI KU","townEn":"KISSHOIN RYUSAKUCHO"},"6018391":{"prefectureJa":"京都府","cityJa":"京都市南区","townJa":"吉祥院大河原町","prefectureEn":"KYOTO FU","cityEn":"KYOTO SHI MINAMI KU","townEn":"KISSHOIN OGAWARACHO"},"6018392":{"prefectureJa":"京都府","cityJa":"京都市南区","townJa":"吉祥院内河原町","prefectureEn":"KYOTO FU","cityEn":"KYOTO SHI MINAMI KU","townEn":"KISSHOIN UCHIGAWARACHO"},"6018393":{"prefectureJa":"京都府","cityJa":"京都市南区","townJa":"吉祥院中河原里西町","prefectureEn":"KYOTO FU","cityEn":"KYOTO SHI MINAMI KU","townEn":"KISSHOINNAKAGAWARA SATONISHICHO"},"6018394":{"prefectureJa":"京都府","cityJa":"京都市南区","townJa":"吉祥院中河原里北町","prefectureEn":"KYOTO FU","cityEn":"KYOTO SHI MINAMI KU","townEn":"KISSHOINNAKAGAWARA SATOKITACHO"},"6018395":{"prefectureJa":"京都府","cityJa":"京都市南区","townJa":"吉祥院中河原西屋敷町","prefectureEn":"KYOTO FU","cityEn":"KYOTO SHI MINAMI KU","townEn":"KISSHOINNAKAGAWARA NISHIYASHIKICHO"},"6018396":{"prefectureJa":"京都府","cityJa":"京都市南区","townJa":"吉祥院中河原里南町","prefectureEn":"KYOTO FU","cityEn":"KYOTO SHI MINAMI KU","townEn":"KISSHOINNAKAGAWARA SATOMINAMICHO"},"6018397":{"prefectureJa":"京都府","cityJa":"京都市南区","townJa":"吉祥院新田壱ノ段町","prefectureEn":"KYOTO FU","cityEn":"KYOTO SHI MINAMI KU","townEn":"KISSHOINSHINDEN ICHINODANCHO"},"6018398":{"prefectureJa":"京都府","cityJa":"京都市南区","townJa":"吉祥院新田参ノ段町","prefectureEn":"KYOTO FU","cityEn":"KYOTO SHI MINAMI KU","townEn":"KISSHOINSHINDEN SANNODANCHO"},"6018399":{"prefectureJa":"京都府","cityJa":"京都市南区","townJa":"吉祥院堤外町","prefectureEn":"KYOTO FU","cityEn":"KYOTO SHI MINAMI KU","townEn":"KISSHOIN TSUTSUMISOTOCHO"},"6018401":{"prefectureJa":"京都府","cityJa":"京都市南区","townJa":"塩屋町","prefectureEn":"KYOTO FU","cityEn":"KYOTO SHI MINAMI KU","townEn":"SHIOYACHO"},"6018402":{"prefectureJa":"京都府","cityJa":"京都市南区","townJa":"大黒町","prefectureEn":"KYOTO FU","cityEn":"KYOTO SHI MINAMI KU","townEn":"DAIKOKUCHO"},"6018403":{"prefectureJa":"京都府","cityJa":"京都市南区","townJa":"古御旅町","prefectureEn":"KYOTO FU","cityEn":"KYOTO SHI MINAMI KU","townEn":"FURUOTABICHO"},"6018404":{"prefectureJa":"京都府","cityJa":"京都市南区","townJa":"西九条小寺町","prefectureEn":"KYOTO FU","cityEn":"KYOTO SHI MINAMI KU","townEn":"NISHIKUJO KODERACHO"},"6018405":{"prefectureJa":"京都府","cityJa":"京都市南区","townJa":"西九条戒光寺町","prefectureEn":"KYOTO FU","cityEn":"KYOTO SHI MINAMI KU","townEn":"NISHIKUJO KAIKOJICHO"},"6018406":{"prefectureJa":"京都府","cityJa":"京都市南区","townJa":"戒光寺町","prefectureEn":"KYOTO FU","cityEn":"KYOTO SHI MINAMI KU","townEn":"KAIKOJICHO"},"6018407":{"prefectureJa":"京都府","cityJa":"京都市南区","townJa":"西九条寺ノ前町","prefectureEn":"KYOTO FU","cityEn":"KYOTO SHI MINAMI KU","townEn":"NISHIKUJO TERANOMAECHO"},"6018411":{"prefectureJa":"京都府","cityJa":"京都市南区","townJa":"西九条北ノ内町","prefectureEn":"KYOTO FU","cityEn":"KYOTO SHI MINAMI KU","townEn":"NISHIKUJO KITANOCHICHO"},"6018412":{"prefectureJa":"京都府","cityJa":"京都市南区","townJa":"西九条院町","prefectureEn":"KYOTO FU","cityEn":"KYOTO SHI MINAMI KU","townEn":"NISHIKUJO IMMACHI"},"6018413":{"prefectureJa":"京都府","cityJa":"京都市南区","townJa":"西九条春日町","prefectureEn":"KYOTO FU","cityEn":"KYOTO SHI MINAMI KU","townEn":"NISHIKUJO KASUGACHO"},"6018414":{"prefectureJa":"京都府","cityJa":"京都市南区","townJa":"西九条蔵王町","prefectureEn":"KYOTO FU","cityEn":"KYOTO SHI MINAMI KU","townEn":"NISHIKUJO ZAOCHO"},"6018415":{"prefectureJa":"京都府","cityJa":"京都市南区","townJa":"西九条西蔵王町","prefectureEn":"KYOTO FU","cityEn":"KYOTO SHI MINAMI KU","townEn":"NISHIKUJO NISHIZAOCHO"},"6018416":{"prefectureJa":"京都府","cityJa":"京都市南区","townJa":"西九条池ノ内町","prefectureEn":"KYOTO FU","cityEn":"KYOTO SHI MINAMI KU","townEn":"NISHIKUJO IKENOCHICHO"},"6018417":{"prefectureJa":"京都府","cityJa":"京都市南区","townJa":"西九条鳥居口町","prefectureEn":"KYOTO FU","cityEn":"KYOTO SHI MINAMI KU","townEn":"NISHIKUJO TORIIGUCHICHO"},"6018421":{"prefectureJa":"京都府","cityJa":"京都市南区","townJa":"西九条藤ノ木町","prefectureEn":"KYOTO FU","cityEn":"KYOTO SHI MINAMI KU","townEn":"NISHIKUJO FUJINOKICHO"},"6018422":{"prefectureJa":"京都府","cityJa":"京都市南区","townJa":"西九条針小路町","prefectureEn":"KYOTO FU","cityEn":"KYOTO SHI MINAMI KU","townEn":"NISHIKUJO HARIKOJICHO"},"6018423":{"prefectureJa":"京都府","cityJa":"京都市南区","townJa":"西九条唐橋町","prefectureEn":"KYOTO FU","cityEn":"KYOTO SHI MINAMI KU","townEn":"NISHIKUJO KARAHASHICHO"},"6018424":{"prefectureJa":"京都府","cityJa":"京都市南区","townJa":"西九条川原城町","prefectureEn":"KYOTO FU","cityEn":"KYOTO SHI MINAMI KU","townEn":"NISHIKUJO KAWARAJOCHO"},"6018425":{"prefectureJa":"京都府","cityJa":"京都市南区","townJa":"西九条南小路町","prefectureEn":"KYOTO FU","cityEn":"KYOTO SHI MINAMI KU","townEn":"NISHIKUJO MINAMIKOJICHO"},"6018426":{"prefectureJa":"京都府","cityJa":"京都市南区","townJa":"西九条猪熊町","prefectureEn":"KYOTO FU","cityEn":"KYOTO SHI MINAMI KU","townEn":"NISHIKUJO INOKUMACHO"},"6018427":{"prefectureJa":"京都府","cityJa":"京都市南区","townJa":"西九条横町","prefectureEn":"KYOTO FU","cityEn":"KYOTO SHI MINAMI KU","townEn":"NISHIKUJO YOKOMACHI"},"6018428":{"prefectureJa":"京都府","cityJa":"京都市南区","townJa":"東寺東門前町","prefectureEn":"KYOTO FU","cityEn":"KYOTO SHI MINAMI KU","townEn":"TOJIHIGASHIMONZENCHO"},"6018431":{"prefectureJa":"京都府","cityJa":"京都市南区","townJa":"西九条島町","prefectureEn":"KYOTO FU","cityEn":"KYOTO SHI MINAMI KU","townEn":"NISHIKUJO SHIMAMACHI"},"6018432":{"prefectureJa":"京都府","cityJa":"京都市南区","townJa":"西九条東島町","prefectureEn":"KYOTO FU","cityEn":"KYOTO SHI MINAMI KU","townEn":"NISHIKUJO HIGASHISHIMAMACHI"},"6018433":{"prefectureJa":"京都府","cityJa":"京都市南区","townJa":"西九条東柳ノ内町","prefectureEn":"KYOTO FU","cityEn":"KYOTO SHI MINAMI KU","townEn":"NISHIKUJO HIGASHIYANAGINOCHICHO"},"6018434":{"prefectureJa":"京都府","cityJa":"京都市南区","townJa":"西九条仏現寺町","prefectureEn":"KYOTO FU","cityEn":"KYOTO SHI MINAMI KU","townEn":"NISHIKUJO BUTSUGENJICHO"},"6018435":{"prefectureJa":"京都府","cityJa":"京都市南区","townJa":"西九条柳ノ内町","prefectureEn":"KYOTO FU","cityEn":"KYOTO SHI MINAMI KU","townEn":"NISHIKUJO YANAGINOCHICHO"},"6018436":{"prefectureJa":"京都府","cityJa":"京都市南区","townJa":"西九条西柳ノ内町","prefectureEn":"KYOTO FU","cityEn":"KYOTO SHI MINAMI KU","townEn":"NISHIKUJO NISHIYANAGINOCHICHO"},"6018437":{"prefectureJa":"京都府","cityJa":"京都市南区","townJa":"西九条比永城町","prefectureEn":"KYOTO FU","cityEn":"KYOTO SHI MINAMI KU","townEn":"NISHIKUJO HIEIJOCHO"},"6018438":{"prefectureJa":"京都府","cityJa":"京都市南区","townJa":"西九条東比永城町","prefectureEn":"KYOTO FU","cityEn":"KYOTO SHI MINAMI KU","townEn":"NISHIKUJO HIGASHIHIEIJOCHO"},"6018439":{"prefectureJa":"京都府","cityJa":"京都市南区","townJa":"西九条開ケ町","prefectureEn":"KYOTO FU","cityEn":"KYOTO SHI MINAMI KU","townEn":"NISHIKUJO KAIGACHO"},"6018441":{"prefectureJa":"京都府","cityJa":"京都市南区","townJa":"西九条南田町","prefectureEn":"KYOTO FU","cityEn":"KYOTO SHI MINAMI KU","townEn":"NISHIKUJO NANDENCHO"},"6018442":{"prefectureJa":"京都府","cityJa":"京都市南区","townJa":"西九条御幸田町","prefectureEn":"KYOTO FU","cityEn":"KYOTO SHI MINAMI KU","townEn":"NISHIKUJO GOKODENCHO"},"6018443":{"prefectureJa":"京都府","cityJa":"京都市南区","townJa":"西九条東御幸田町","prefectureEn":"KYOTO FU","cityEn":"KYOTO SHI MINAMI KU","townEn":"NISHIKUJO HIGASHIGOKODENCHO"},"6018444":{"prefectureJa":"京都府","cityJa":"京都市南区","townJa":"西九条森本町","prefectureEn":"KYOTO FU","cityEn":"KYOTO SHI MINAMI KU","townEn":"NISHIKUJO MORIMOTOCHO"},"6018445":{"prefectureJa":"京都府","cityJa":"京都市南区","townJa":"西九条菅田町","prefectureEn":"KYOTO FU","cityEn":"KYOTO SHI MINAMI KU","townEn":"NISHIKUJO SUGATACHO"},"6018446":{"prefectureJa":"京都府","cityJa":"京都市南区","townJa":"西九条高畠町","prefectureEn":"KYOTO FU","cityEn":"KYOTO SHI MINAMI KU","townEn":"NISHIKUJO TAKAHATACHO"},"6018447":{"prefectureJa":"京都府","cityJa":"京都市南区","townJa":"西九条唐戸町","prefectureEn":"KYOTO FU","cityEn":"KYOTO SHI MINAMI KU","townEn":"NISHIKUJO KARATOCHO"},"6018448":{"prefectureJa":"京都府","cityJa":"京都市南区","townJa":"西九条豊田町","prefectureEn":"KYOTO FU","cityEn":"KYOTO SHI MINAMI KU","townEn":"NISHIKUJO TOYODACHO"},"6018449":{"prefectureJa":"京都府","cityJa":"京都市南区","townJa":"西九条大国町","prefectureEn":"KYOTO FU","cityEn":"KYOTO SHI MINAMI KU","townEn":"NISHIKUJO OKUNICHO"},"6018451":{"prefectureJa":"京都府","cityJa":"京都市南区","townJa":"唐橋川久保町","prefectureEn":"KYOTO FU","cityEn":"KYOTO SHI MINAMI KU","townEn":"KARAHASHI KAWAKUBOCHO"},"6018452":{"prefectureJa":"京都府","cityJa":"京都市南区","townJa":"唐橋堂ノ前町","prefectureEn":"KYOTO FU","cityEn":"KYOTO SHI MINAMI KU","townEn":"KARAHASHI DONOMAECHO"},"6018453":{"prefectureJa":"京都府","cityJa":"京都市南区","townJa":"唐橋羅城門町","prefectureEn":"KYOTO FU","cityEn":"KYOTO SHI MINAMI KU","townEn":"KARAHASHI RAJOMONCHO"},"6018454":{"prefectureJa":"京都府","cityJa":"京都市南区","townJa":"唐橋経田町","prefectureEn":"KYOTO FU","cityEn":"KYOTO SHI MINAMI KU","townEn":"KARAHASHI KEIDENCHO"},"6018455":{"prefectureJa":"京都府","cityJa":"京都市南区","townJa":"唐橋芦辺町","prefectureEn":"KYOTO FU","cityEn":"KYOTO SHI MINAMI KU","townEn":"KARAHASHI ASHIBECHO"},"6018456":{"prefectureJa":"京都府","cityJa":"京都市南区","townJa":"唐橋南琵琶町","prefectureEn":"KYOTO FU","cityEn":"KYOTO SHI MINAMI KU","townEn":"KARAHASHI MINAMIBIWACHO"},"6018457":{"prefectureJa":"京都府","cityJa":"京都市南区","townJa":"唐橋琵琶町","prefectureEn":"KYOTO FU","cityEn":"KYOTO SHI MINAMI KU","townEn":"KARAHASHI BIWACHO"},"6018461":{"prefectureJa":"京都府","cityJa":"京都市南区","townJa":"唐橋門脇町","prefectureEn":"KYOTO FU","cityEn":"KYOTO SHI MINAMI KU","townEn":"KARAHASHI KADOWAKICHO"},"6018462":{"prefectureJa":"京都府","cityJa":"京都市南区","townJa":"唐橋井園町","prefectureEn":"KYOTO FU","cityEn":"KYOTO SHI MINAMI KU","townEn":"KARAHASHI ISONOCHO"},"6018463":{"prefectureJa":"京都府","cityJa":"京都市南区","townJa":"唐橋赤金町","prefectureEn":"KYOTO FU","cityEn":"KYOTO SHI MINAMI KU","townEn":"KARAHASHI AKAKANECHO"},"6018464":{"prefectureJa":"京都府","cityJa":"京都市南区","townJa":"唐橋高田町","prefectureEn":"KYOTO FU","cityEn":"KYOTO SHI MINAMI KU","townEn":"KARAHASHI TAKADACHO"},"6018465":{"prefectureJa":"京都府","cityJa":"京都市南区","townJa":"唐橋花園町","prefectureEn":"KYOTO FU","cityEn":"KYOTO SHI MINAMI KU","townEn":"KARAHASHI HANAZONOCHO"},"6018466":{"prefectureJa":"京都府","cityJa":"京都市南区","townJa":"唐橋西寺町","prefectureEn":"KYOTO FU","cityEn":"KYOTO SHI MINAMI KU","townEn":"KARAHASHI SAIJICHO"},"6018467":{"prefectureJa":"京都府","cityJa":"京都市南区","townJa":"唐橋大宮尻町","prefectureEn":"KYOTO FU","cityEn":"KYOTO SHI MINAMI KU","townEn":"KARAHASHI OMIYAJIRICHO"},"6018468":{"prefectureJa":"京都府","cityJa":"京都市南区","townJa":"唐橋西平垣町","prefectureEn":"KYOTO FU","cityEn":"KYOTO SHI MINAMI KU","townEn":"KARAHASHI NISHIHIRAGAKICHO"},"6018469":{"prefectureJa":"京都府","cityJa":"京都市南区","townJa":"唐橋平垣町","prefectureEn":"KYOTO FU","cityEn":"KYOTO SHI MINAMI KU","townEn":"KARAHASHI HIRAGAKICHO"},"6018471":{"prefectureJa":"京都府","cityJa":"京都市南区","townJa":"八条町","prefectureEn":"KYOTO FU","cityEn":"KYOTO SHI MINAMI KU","townEn":"HACHIJOCHO"},"6018472":{"prefectureJa":"京都府","cityJa":"京都市南区","townJa":"八条坊門町","prefectureEn":"KYOTO FU","cityEn":"KYOTO SHI MINAMI KU","townEn":"HACHIJO BOMONCHO"},"6018473":{"prefectureJa":"京都府","cityJa":"京都市南区","townJa":"九条町","prefectureEn":"KYOTO FU","cityEn":"KYOTO SHI MINAMI KU","townEn":"KUJOCHO"},"6018474":{"prefectureJa":"京都府","cityJa":"京都市南区","townJa":"四ツ塚町","prefectureEn":"KYOTO FU","cityEn":"KYOTO SHI MINAMI KU","townEn":"YOTSUZUKACHO"},"6018475":{"prefectureJa":"京都府","cityJa":"京都市南区","townJa":"八条内田町","prefectureEn":"KYOTO FU","cityEn":"KYOTO SHI MINAMI KU","townEn":"HACHIJO UCHIDACHO"},"6018476":{"prefectureJa":"京都府","cityJa":"京都市南区","townJa":"八条寺内町","prefectureEn":"KYOTO FU","cityEn":"KYOTO SHI MINAMI KU","townEn":"HACHIJO TERANOCHICHO"},"6018477":{"prefectureJa":"京都府","cityJa":"京都市南区","townJa":"八条源町","prefectureEn":"KYOTO FU","cityEn":"KYOTO SHI MINAMI KU","townEn":"HACHIJO MINAMOTOCHO"},"6018478":{"prefectureJa":"京都府","cityJa":"京都市南区","townJa":"東寺町","prefectureEn":"KYOTO FU","cityEn":"KYOTO SHI MINAMI KU","townEn":"TOJICHO"}}